Workbook
Name BaseTicketsDay: Supuestos!$B$13
Name ItemsPerTicket: Supuestos!$B$14
Name Seasonality: Supuestos!$C$19:$N$19
Name OpeningDays: Supuestos!$C$20:$N$20
Name Ramp: Supuestos!$C$21:$N$21
Name ScenarioMatrix: Supuestos!$D$27:$F$36
Name Equity: Supuestos!$B$41
Name LoanAmount: Supuestos!$B$42
Name LoanRate: Supuestos!$B$43
Name LoanMonths: Supuestos!$B$44
Name OpeningCash: Supuestos!$B$45
Name WC0: Supuestos!$B$46
Name MinCash: Supuestos!$B$47
Name LoanPayment: Supuestos!$B$48
Name TaxRate: Supuestos!$B$53
Name InventoryDays: Supuestos!$B$54
Name PayableDays: Supuestos!$B$55
Name ReceivableDays: Supuestos!$B$56
Name RentGrowth: Supuestos!$B$61
Name FixedMarketingGrowth: Supuestos!$B$62
Name ProductPVP: Productos!$D$5:$D$12
Name ProductVAT: Productos!$E$5:$E$12
Name ProductNetPrice: Productos!$F$5:$F$12
Name ProductCost: Productos!$G$5:$G$12
Name ProductMix: Productos!$H$5:$H$12
Name ProductWaste: Productos!$I$5:$I$12
Name ProductCostAdj: Productos!$J$5:$J$12
Name ProductUnitMargin: Productos!$K$5:$K$12
Name WeightedNetPrice: Productos!$F$13
Name WeightedCostAdj: Productos!$J$13
Name StaffSalary: Personal!$B$5:$B$8
Name StaffFTE_Y1: Personal!$C$5:$C$8
Name StaffFTE_Y2: Personal!$D$5:$D$8
Name StaffFTE_Y3: Personal!$E$5:$E$8
Name StaffCostByYear: Personal!$F$9:$H$9
Name EmployerSS: Personal!$B$11
Name SalaryGrowth: Personal!$B$12
Name RentMonth: Costos!$B$6
Name UtilitiesMonth: Costos!$B$7
Name FixedServicesMonth: Costos!$B$8
Name FixedMarketingMonth: Costos!$B$9
Name OtherOpexMonth: Costos!$B$10
Name CapexAmount: Costos!$B$15:$B$20
Name CapexLife: Costos!$C$15:$C$20
Name TotalCapex: Costos!$B$21
Name MonthlyDepreciation: Costos!$E$21
Name MaintenanceCapexPct: Costos!$B$24

Sheet Portada
B2: Cafetería Aurora
B3: Modelo financiero 2026–2028
B4: Café de especialidad · Zaragoza · EUR
B6: QUÉ ES ESTE LIBRO
B7: Un modelo mensual de 36 meses, tres escenarios (Pesimista, Base y Optimista), cuenta de resultados, caja, deuda, impuestos, punto de equilibrio y payback. Todas las celdas blancas son fórmulas: cambia una celda amarilla y el libro se recalcula.
B10: CÓMO USARLO
B11: 1. Elige el escenario en Resumen B4 (1 Pesimista, 2 Base, 3 Optimista).
B12: 2. Cambia solo las celdas amarillas de Supuestos, Productos, Personal y Costos.
B13: 3. No edites celdas blancas: son fórmulas vivas.
B14: 4. Revisa los checks verdes de Supuestos y de cada hoja de escenario.
B15: 5. Descarga la versión web y la guía desde el README del repositorio.
B17: LEYENDA
B18: Entrada editable | C18: Celda amarilla: puedes cambiarla. Solo en las hojas de entrada y selectores.
B19: Fórmula (no editar) | C19: Celda blanca: se recalcula. Si la sobrescribes, rompes la trazabilidad.
B20: OK | C20: Verde si cuadra; rojo si hay que revisar.
B22: FUENTE DE VERDAD
B23: data/model.json | C23: El contrato de supuestos. El libro, el sitio y los tests se generan desde él.
B25: Versión | C25: 1.0 · 25/10/2026
B26: Autor | C26: Cafetería Aurora · modelo educativo
B27: Aviso | C27: Este modelo es educativo. No es asesoramiento financiero, fiscal ni legal.

Sheet Supuestos
A1: Supuestos
A2: Todo lo que se puede cambiar vive aquí. Las celdas amarillas son entradas; los checks, fórmulas.
A4: IDENTIDAD Y CALENDARIO
A5: Nombre | B5: Cafetería Aurora
A6: Moneda | B6: EUR
A7: Inicio | B7: 46023
A8: Meses | B8: 36
A9: Año base | B9: 2026
A10: Modelo | B10: Mensual, 36 meses
A12: DEMANDA
A13: Tickets/día en régimen | B13: 360
A14: Ítems por ticket | B14: 1.35
A15: Días operativos al año | B15: =SUM(C20:N20)
A17: ESTACIONALIDAD, DÍAS OPERATIVOS Y RAMPA
A18: Concepto | B18: Unidad | C18: ene | D18: feb | E18: mar | F18: abr | G18: may | H18: jun | I18: jul | J18: ago | K18: sep | L18: oct | M18: nov | N18: dic | O18: Total
A19: Estacionalidad | B19: factor | C19: 0.92 | D19: 0.93 | E19: 1.02 | F19: 1.04 | G19: 1.08 | H19: 1.06 | I19: 0.88 | J19: 0.72 | K19: 1.06 | L19: 1.09 | M19: 1.04 | N19: 1.16 | O19: =SUM(C19:N19)
A20: Días operativos | B20: días | C20: 27 | D20: 24 | E20: 27 | F20: 26 | G20: 27 | H20: 26 | I20: 27 | J20: 24 | K20: 26 | L20: 27 | M20: 25 | N20: 26 | O20: =SUM(C20:N20)
A21: Rampa año 1 | B21: factor | C21: 0.75 | D21: 0.82 | E21: 0.88 | F21: 0.93 | G21: 0.97 | H21: 1 | I21: 1 | J21: 1 | K21: 1 | L21: 1 | M21: 1 | N21: 1 | O21: =SUM(C21:N21)/12
A22: Nota: la estacionalidad suma 12,00 y los días 312. La rampa solo se aplica en 2026.
A25: MATRIZ DE ESCENARIOS
A26: # | B26: Variable | C26: Unidad | D26: Pesimista | E26: Base | F26: Optimista
A27: 1 | B27: Factor de demanda año 1 | C27: × | D27: 0.88 | E27: 1 | F27: 1.08
A28: 2 | B28: Crecimiento anual de demanda | C28: % | D28: 0.015 | E28: 0.04 | F28: 0.06
A29: 3 | B29: Crecimiento anual de precios | C29: % | D29: 0.015 | E29: 0.025 | F29: 0.032
A30: 4 | B30: Inflación anual de costes de producto | C30: % | D30: 0.045 | E30: 0.035 | F30: 0.028
A31: 5 | B31: Factor de personal | C31: × | D31: 1.03 | E31: 1 | F31: 0.98
A32: 6 | B32: Factor de alquiler | C32: × | D32: 1.05 | E32: 1 | F32: 0.96
A33: 7 | B33: Inflación de suministros y servicios | C33: % | D33: 0.06 | E33: 0.04 | F33: 0.03
A34: 8 | B34: Marketing variable | C34: % ingresos | D34: 0.02 | E34: 0.03 | F34: 0.04
A35: 9 | B35: Factor de otros gastos | C35: × | D35: 1.08 | E35: 1 | F35: 0.95
A36: 10 | B36: Crecimiento de otros gastos | C36: % | D36: 0.03 | E36: 0.025 | F36: 0.02
A37: Excepción intencional: marketing variable es más bajo en Pesimista (2 %) porque es una respuesta de gestión, no un coste externo.
A40: FINANCIACIÓN Y CAJA INICIAL
A41: Equity aportado | B41: 90000
A42: Préstamo | B42: 70000
A43: Tipo nominal anual | B43: 0.075
A44: Plazo | B44: 60
A45: Caja de apertura | B45: 21500
A46: Stock inicial (capital circulante t0) | B46: 6500
A47: Caja mínima de política | B47: 10000
A48: Cuota mensual del préstamo | B48: =PMT(B43/12,B44,-B42)
A49: La caja de apertura y el stock son usos financiados con equity y deuda; no son ingresos.
A52: FISCALIDAD Y CAPITAL CIRCULANTE
A53: Tipo de sociedades | B53: 0.25
A54: Días de inventario | B54: 18
A55: Días de proveedor | B55: 30
A56: Días de cobro | B56: 0
A57: Pérdidas compensables sin límite por ser pyme (<1 M€). Provisión mensual = cuota anual / 12.
A60: CRECIMIENTOS ESTRUCTURALES
A61: Crecimiento anual del alquiler | B61: 0.02
A62: Crecimiento anual del marketing fijo | B62: 0.025
A63: La inflación de precios, costes y servicios vive en la matriz de escenarios; aquí solo los crecimientos estructurales.
A65: CONTROLES DE INTEGRIDAD
A66: Check | B66: Valor | C66: Estado
A67: Mix de producto (debe ser 100 %) | B67: =SUM(Productos!H5:H12) | C67: =IF(ABS(B67-1)<0.0001,"OK","Revisar")
A68: Estacionalidad (debe ser 12,00) | B68: =SUM(C19:N19) | C68: =IF(ABS(B68-12)<0.0001,"OK","Revisar")
A69: Días operativos (deben ser 312) | B69: =SUM(C20:N20) | C69: =IF(B69=312,"OK","Revisar")
A70: Capex inicial (debe ser 132.000 €) | B70: =Costos!B21 | C70: =IF(B70=132000,"OK","Revisar")
A71: Fuentes = usos | B71: =B41+B42 | C71: =IF(B71=Costos!B30,"OK","Revisar")
A72: Orden de escenarios (demanda y precio) | B72: =IF(AND(D27<E27,E27<F27,D28<E28,E28<F28,D29<E29,E29<F29),"OK","Revisar orden")
A73: Orden de costes (inverso) | B73: =IF(AND(D30>E30,E30>F30,D31>E31,E31>F31,D32>E32,E32>F32,D34>E34,E34>F34,D35>E35,E35>F35,D36>E36,E36>F36),"OK","Revisar orden")
A75: Si algún check dice «Revisar», no uses las cifras: corrige la entrada.

Sheet Productos
A1: Productos
A2: PVP con IVA en la carta; precio neto y coste ajustado por merma en el modelo.
A4: # | B4: Producto | C4: Categoría | D4: PVP | E4: IVA | F4: Precio neto | G4: Coste unitario | H4: Mix | I4: Merma | J4: Coste ajustado | K4: Margen unitario | L4: Margen % | M4: Contribución | N4: Check PVP
A5: 1 | B5: Espresso | C5: Café | D5: 1.7 | E5: 0.1 | F5: =D5/(1+E5) | G5: 0.42 | H5: 0.22 | I5: 0.04 | J5: =G5/(1-I5) | K5: =F5-J5 | L5: =IFERROR(K5/F5,0) | M5: =F5*H5 | N5: =IF(F5>J5,1,0)
A6: 2 | B6: Flat white | C6: Café con leche | D6: 2.8 | E6: 0.1 | F6: =D6/(1+E6) | G6: 0.72 | H6: 0.2 | I6: 0.04 | J6: =G6/(1-I6) | K6: =F6-J6 | L6: =IFERROR(K6/F6,0) | M6: =F6*H6 | N6: =IF(F6>J6,1,0)
A7: 3 | B7: Cappuccino | C7: Café con leche | D7: 2.6 | E7: 0.1 | F7: =D7/(1+E7) | G7: 0.66 | H7: 0.1 | I7: 0.04 | J7: =G7/(1-I7) | K7: =F7-J7 | L7: =IFERROR(K7/F7,0) | M7: =F7*H7 | N7: =IF(F7>J7,1,0)
A8: 4 | B8: Latte | C8: Café con leche | D8: 2.9 | E8: 0.1 | F8: =D8/(1+E8) | G8: 0.74 | H8: 0.13 | I8: 0.04 | J8: =G8/(1-I8) | K8: =F8-J8 | L8: =IFERROR(K8/F8,0) | M8: =F8*H8 | N8: =IF(F8>J8,1,0)
A9: 5 | B9: Cold brew | C9: Café frío | D9: 3.4 | E9: 0.1 | F9: =D9/(1+E9) | G9: 0.95 | H9: 0.08 | I9: 0.05 | J9: =G9/(1-I9) | K9: =F9-J9 | L9: =IFERROR(K9/F9,0) | M9: =F9*H9 | N9: =IF(F9>J9,1,0)
A10: 6 | B10: Croissant | C10: Panadería | D10: 2.3 | E10: 0.1 | F10: =D10/(1+E10) | G10: 0.82 | H10: 0.14 | I10: 0.08 | J10: =G10/(1-I10) | K10: =F10-J10 | L10: =IFERROR(K10/F10,0) | M10: =F10*H10 | N10: =IF(F10>J10,1,0)
A11: 7 | B11: Tostada | C11: Salado | D11: 3.9 | E11: 0.1 | F11: =D11/(1+E11) | G11: 1.18 | H11: 0.09 | I11: 0.06 | J11: =G11/(1-I11) | K11: =F11-J11 | L11: =IFERROR(K11/F11,0) | M11: =F11*H11 | N11: =IF(F11>J11,1,0)
A12: 8 | B12: Bolsa café 250 g | C12: Retail | D12: 10.5 | E12: 0.1 | F12: =D12/(1+E12) | G12: 4.6 | H12: 0.04 | I12: 0.02 | J12: =G12/(1-I12) | K12: =F12-J12 | L12: =IFERROR(K12/F12,0) | M12: =F12*H12 | N12: =IF(F12>J12,1,0)
B13: Total / ponderado | D13: =SUMPRODUCT(D5:D12,H5:H12) | E13: ="" | F13: =SUMPRODUCT(F5:F12,H5:H12) | G13: ="" | H13: =SUM(H5:H12) | I13: ="" | J13: =SUMPRODUCT(J5:J12,H5:H12) | K13: =F13-J13 | L13: =IFERROR(K13/F13,0) | M13: =SUM(M5:M12) | N13: =SUM(N5:N12)
A14: Check | B14: Mix 100 % | C14: =IF(ABS(H13-1)<0.0001,"OK","Revisar") | D14: PVP > coste | E14: =IF(N13=8,"OK","Revisar")
A15: La merma se aplica al coste, nunca al precio. El mix se mantiene constante en los tres años.

Sheet Personal
A1: Personal
A2: Coste empresa = salario bruto × FTE × (1 + cotización) × (1 + crecimiento)^(año−1).
A4: Rol | B4: Salario bruto anual | C4: FTE 2026 | D4: FTE 2027 | E4: FTE 2028 | F4: Coste 2026 | G4: Coste 2027 | H4: Coste 2028
A5: Gerente | B5: 30000 | C5: 1 | D5: 1 | E5: 1 | F5: =B5*C5*(1+$B$11) | G5: =B5*(1+$B$12)*D5*(1+$B$11) | H5: =B5*(1+$B$12)^2*E5*(1+$B$11)
A6: Barista | B6: 23000 | C6: 1 | D6: 1.5 | E6: 1.5 | F6: =B6*C6*(1+$B$11) | G6: =B6*(1+$B$12)*D6*(1+$B$11) | H6: =B6*(1+$B$12)^2*E6*(1+$B$11)
A7: Ayudante de cocina | B7: 21000 | C7: 1 | D7: 1 | E7: 1 | F7: =B7*C7*(1+$B$11) | G7: =B7*(1+$B$12)*D7*(1+$B$11) | H7: =B7*(1+$B$12)^2*E7*(1+$B$11)
A8: Fin de semana | B8: 20000 | C8: 0.5 | D8: 0.5 | E8: 0.5 | F8: =B8*C8*(1+$B$11) | G8: =B8*(1+$B$12)*D8*(1+$B$11) | H8: =B8*(1+$B$12)^2*E8*(1+$B$11)
A9: Total | C9: =SUM(C5:C8) | D9: =SUM(D5:D8) | E9: =SUM(E5:E8) | F9: =SUM(F5:F8) | G9: =SUM(G5:G8) | H9: =SUM(H5:H8)
A11: Cotización empresarial | B11: 0.315
A12: Crecimiento salarial | B12: 0.03
A13: El barista pasa de 1,0 a 1,5 FTE en 2027. No se modelan horas extras, bajas ni bonificaciones.

Sheet Costos
A1: Costos
A2: Costes fijos, capex, mantenimiento y cuadre de fuentes y usos.
A4: COSTES FIJOS
A5: Concepto | B5: €/mes año 1 | C5: €/año año 1 | D5: Indexación | E5: Nota
A6: Alquiler | B6: 1900 | C6: =B6*12 | D6: 2,0 % anual × factor de alquiler | E6: 92 m² a 20,65 €/m²/mes
A7: Suministros | B7: 1450 | C7: =B7*12 | D7: Inflación de servicios del escenario | E7: Luz, gas, agua y residuos
A8: Servicios fijos | B8: 780 | C8: =B8*12 | D8: Inflación de servicios del escenario | E8: Internet, TPV, software, seguro, gestoría y alarma
A9: Marketing fijo | B9: 450 | C9: =B9*12 | D9: 2,5 % anual | E9: Contenido, fotografía e impresos
A10: Otros gastos | B10: 1100 | C10: =B10*12 | D10: Crecimiento de otros × factor | E10: Limpieza, mantenimiento, formación, banca y comisiones
A11: Total | B11: =SUM(B6:B10) | C11: =SUM(C6:C10)
A13: CAPEX INICIAL
A14: Activo | B14: Importe | C14: Vida útil | D14: Amortización anual | E14: Amortización mensual
A15: Obra y adecuación | B15: 65000 | C15: 10 | D15: =B15/C15 | E15: =D15/12
A16: Maquinaria de café | B16: 28000 | C16: 7 | D16: =B16/C16 | E16: =D16/12
A17: Mobiliario y menaje | B17: 15000 | C17: 8 | D17: =B17/C17 | E17: =D17/12
A18: Equipo de cocina y frío | B18: 12000 | C18: 8 | D18: =B18/C18 | E18: =D18/12
A19: Tecnología y TPV | B19: 7000 | C19: 4 | D19: =B19/C19 | E19: =D19/12
A20: Licencias y apertura | B20: 5000 | C20: 5 | D20: =B20/C20 | E20: =D20/12
A21: Total | B21: =SUM(B15:B20) | D21: =SUM(D15:D20) | E21: =SUM(E15:E20)
A23: CAPEX DE MANTENIMIENTO
A24: Capex de mantenimiento | B24: 0.015 | C24: de ingresos netos, salida de caja de inversión
A26: CUADRE DE FUENTES Y USOS
A27: Concepto | B27: Importe
A28: Capex inicial | B28: =B21
A29: Stock inicial | B29: =Supuestos!B46
A30: Total usos (capex + stock + caja) | B30: =B21+Supuestos!B46+Supuestos!B45
A31: Total fuentes (equity + deuda) | B31: =Supuestos!B41+Supuestos!B42
A32: Check | B32: =IF(B30=B31,"OK","Revisar")
A34: La caja de apertura es un uso, no un ingreso. El capex de mantenimiento no genera una capa adicional de amortización.

Sheet Pesimista
A1: Cafetería Aurora — Escenario Pesimista
A2: EUR, sin IVA. Solo se editan las hojas de entrada.
A3: Selector (1/2/3): | B3: 1 | C3: 1 = Pesimista · 2 = Base · 3 = Optimista
A4: Escenario: | B4: =CHOOSE(B3,"Pesimista","Base","Optimista") | C4: Cambia el selector para ver el mismo modelo con los supuestos de otro escenario.
A5: Índice de mes | B5: mes | C5: 1 | D5: =C5+1 | E5: =D5+1 | F5: =E5+1 | G5: =F5+1 | H5: =G5+1 | I5: =H5+1 | J5: =I5+1 | K5: =J5+1 | ... AL5: =AK5+1
A6: Fecha | B6: fecha | C6: =DATE(2026,1,1) | D6: =EDATE(C6,1) | E6: =EDATE(D6,1) | F6: =EDATE(E6,1) | G6: =EDATE(F6,1) | H6: =EDATE(G6,1) | I6: =EDATE(H6,1) | J6: =EDATE(I6,1) | K6: =EDATE(J6,1) | ... AL6: =EDATE(AK6,1)
A7: Año | B7: 1–3 | C7: =ROUNDUP(C5/12,0) | D7: =ROUNDUP(D5/12,0) | E7: =ROUNDUP(E5/12,0) | F7: =ROUNDUP(F5/12,0) | G7: =ROUNDUP(G5/12,0) | H7: =ROUNDUP(H5/12,0) | I7: =ROUNDUP(I5/12,0) | J7: =ROUNDUP(J5/12,0) | ... AL7: =ROUNDUP(AL5/12,0)
A8: Mes | B8: 1–12 | C8: =MOD(C5-1,12)+1 | D8: =MOD(D5-1,12)+1 | E8: =MOD(E5-1,12)+1 | F8: =MOD(F5-1,12)+1 | G8: =MOD(G5-1,12)+1 | H8: =MOD(H5-1,12)+1 | I8: =MOD(I5-1,12)+1 | J8: =MOD(J5-1,12)+1 | ... AL8: =MOD(AL5-1,12)+1
A9: Días operativos | B9: días | C9: =INDEX(OpeningDays,1,C8) | D9: =INDEX(OpeningDays,1,D8) | E9: =INDEX(OpeningDays,1,E8) | F9: =INDEX(OpeningDays,1,F8) | G9: =INDEX(OpeningDays,1,G8) | H9: =INDEX(OpeningDays,1,H8) | I9: =INDEX(OpeningDays,1,I8) | J9: =INDEX(OpeningDays,1,J8) | ... AL9: =INDEX(OpeningDays,1,AL8) | AM9: =SUM(C9:N9) | AN9: =SUM(O9:Z9) | AO9: =SUM(AA9:AL9) | AP9: =SUM(AM9:AO9)
A11: CUENTA DE RESULTADOS
A12: Tickets/día | B12: tickets/día | C12: =BaseTicketsDay*INDEX(ScenarioMatrix,1,$B$3)*(1+INDEX(ScenarioMatrix,2,$B$3))^(1-1)*INDEX(Seasonality,1,C8)*IF(1=1,INDEX(Ramp,1,C8),1) | D12: =BaseTicketsDay*INDEX(ScenarioMatrix,1,$B$3)*(1+INDEX(ScenarioMatrix,2,$B$3))^(1-1)*INDEX(Seasonality,1,D8)*IF(1=1,INDEX(Ramp,1,D8),1) | E12: =BaseTicketsDay*INDEX(ScenarioMatrix,1,$B$3)*(1+INDEX(ScenarioMatrix,2,$B$3))^(1-1)*INDEX(Seasonality,1,E8)*IF(1=1,INDEX(Ramp,1,E8),1) | F12: =BaseTicketsDay*INDEX(ScenarioMatrix,1,$B$3)*(1+INDEX(ScenarioMatrix,2,$B$3))^(1-1)*INDEX(Seasonality,1,F8)*IF(1=1,INDEX(Ramp,1,F8),1) | G12: =BaseTicketsDay*INDEX(ScenarioMatrix,1,$B$3)*(1+INDEX(ScenarioMatrix,2,$B$3))^(1-1)*INDEX(Seasonality,1,G8)*IF(1=1,INDEX(Ramp,1,G8),1) | H12: =BaseTicketsDay*INDEX(ScenarioMatrix,1,$B$3)*(1+INDEX(ScenarioMatrix,2,$B$3))^(1-1)*INDEX(Seasonality,1,H8)*IF(1=1,INDEX(Ramp,1,H8),1) | I12: =BaseTicketsDay*INDEX(ScenarioMatrix,1,$B$3)*(1+INDEX(ScenarioMatrix,2,$B$3))^(1-1)*INDEX(Seasonality,1,I8)*IF(1=1,INDEX(Ramp,1,I8),1) | J12: =BaseTicketsDay*INDEX(ScenarioMatrix,1,$B$3)*(1+INDEX(ScenarioMatrix,2,$B$3))^(1-1)*INDEX(Seasonality,1,J8)*IF(1=1,INDEX(Ramp,1,J8),1) | ... N12: =BaseTicketsDay*INDEX(ScenarioMatrix,1,$B$3)*(1+INDEX(ScenarioMatrix,2,$B$3))^(1-1)*INDEX(Seasonality,1,N8)*IF(1=1,INDEX(Ramp,1,N8),1) | O12: =BaseTicketsDay*INDEX(ScenarioMatrix,1,$B$3)*(1+INDEX(ScenarioMatrix,2,$B$3))^(2-1)*INDEX(Seasonality,1,O8)*IF(2=1,INDEX(Ramp,1,O8),1) | P12: =BaseTicketsDay*INDEX(ScenarioMatrix,1,$B$3)*(1+INDEX(ScenarioMatrix,2,$B$3))^(2-1)*INDEX(Seasonality,1,P8)*IF(2=1,INDEX(Ramp,1,P8),1) | Q12: =BaseTicketsDay*INDEX(ScenarioMatrix,1,$B$3)*(1+INDEX(ScenarioMatrix,2,$B$3))^(2-1)*INDEX(Seasonality,1,Q8)*IF(2=1,INDEX(Ramp,1,Q8),1) | R12: =BaseTicketsDay*INDEX(ScenarioMatrix,1,$B$3)*(1+INDEX(ScenarioMatrix,2,$B$3))^(2-1)*INDEX(Seasonality,1,R8)*IF(2=1,INDEX(Ramp,1,R8),1) | S12: =BaseTicketsDay*INDEX(ScenarioMatrix,1,$B$3)*(1+INDEX(ScenarioMatrix,2,$B$3))^(2-1)*INDEX(Seasonality,1,S8)*IF(2=1,INDEX(Ramp,1,S8),1) | T12: =BaseTicketsDay*INDEX(ScenarioMatrix,1,$B$3)*(1+INDEX(ScenarioMatrix,2,$B$3))^(2-1)*INDEX(Seasonality,1,T8)*IF(2=1,INDEX(Ramp,1,T8),1) | U12: =BaseTicketsDay*INDEX(ScenarioMatrix,1,$B$3)*(1+INDEX(ScenarioMatrix,2,$B$3))^(2-1)*INDEX(Seasonality,1,U8)*IF(2=1,INDEX(Ramp,1,U8),1) | V12: =BaseTicketsDay*INDEX(ScenarioMatrix,1,$B$3)*(1+INDEX(ScenarioMatrix,2,$B$3))^(2-1)*INDEX(Seasonality,1,V8)*IF(2=1,INDEX(Ramp,1,V8),1) | ... Z12: =BaseTicketsDay*INDEX(ScenarioMatrix,1,$B$3)*(1+INDEX(ScenarioMatrix,2,$B$3))^(2-1)*INDEX(Seasonality,1,Z8)*IF(2=1,INDEX(Ramp,1,Z8),1) | AA12: =BaseTicketsDay*INDEX(ScenarioMatrix,1,$B$3)*(1+INDEX(ScenarioMatrix,2,$B$3))^(3-1)*INDEX(Seasonality,1,AA8)*IF(3=1,INDEX(Ramp,1,AA8),1) | AB12: =BaseTicketsDay*INDEX(ScenarioMatrix,1,$B$3)*(1+INDEX(ScenarioMatrix,2,$B$3))^(3-1)*INDEX(Seasonality,1,AB8)*IF(3=1,INDEX(Ramp,1,AB8),1) | AC12: =BaseTicketsDay*INDEX(ScenarioMatrix,1,$B$3)*(1+INDEX(ScenarioMatrix,2,$B$3))^(3-1)*INDEX(Seasonality,1,AC8)*IF(3=1,INDEX(Ramp,1,AC8),1) | AD12: =BaseTicketsDay*INDEX(ScenarioMatrix,1,$B$3)*(1+INDEX(ScenarioMatrix,2,$B$3))^(3-1)*INDEX(Seasonality,1,AD8)*IF(3=1,INDEX(Ramp,1,AD8),1) | AE12: =BaseTicketsDay*INDEX(ScenarioMatrix,1,$B$3)*(1+INDEX(ScenarioMatrix,2,$B$3))^(3-1)*INDEX(Seasonality,1,AE8)*IF(3=1,INDEX(Ramp,1,AE8),1) | AF12: =BaseTicketsDay*INDEX(ScenarioMatrix,1,$B$3)*(1+INDEX(ScenarioMatrix,2,$B$3))^(3-1)*INDEX(Seasonality,1,AF8)*IF(3=1,INDEX(Ramp,1,AF8),1) | AG12: =BaseTicketsDay*INDEX(ScenarioMatrix,1,$B$3)*(1+INDEX(ScenarioMatrix,2,$B$3))^(3-1)*INDEX(Seasonality,1,AG8)*IF(3=1,INDEX(Ramp,1,AG8),1) | AH12: =BaseTicketsDay*INDEX(ScenarioMatrix,1,$B$3)*(1+INDEX(ScenarioMatrix,2,$B$3))^(3-1)*INDEX(Seasonality,1,AH8)*IF(3=1,INDEX(Ramp,1,AH8),1) | ... AL12: =BaseTicketsDay*INDEX(ScenarioMatrix,1,$B$3)*(1+INDEX(ScenarioMatrix,2,$B$3))^(3-1)*INDEX(Seasonality,1,AL8)*IF(3=1,INDEX(Ramp,1,AL8),1) | AM12: =SUM(C12:N12) | AN12: =SUM(O12:Z12) | AO12: =SUM(AA12:AL12) | AP12: =SUM(AM12:AO12)
A13: Tickets | B13: tickets | C13: =C12*C9 | D13: =D12*D9 | E13: =E12*E9 | F13: =F12*F9 | G13: =G12*G9 | H13: =H12*H9 | I13: =I12*I9 | J13: =J12*J9 | ... AL13: =AL12*AL9 | AM13: =SUM(C13:N13) | AN13: =SUM(O13:Z13) | AO13: =SUM(AA13:AL13) | AP13: =SUM(AM13:AO13)
A14: Ítems vendidos | B14: ítems | C14: =C13*ItemsPerTicket | D14: =D13*ItemsPerTicket | E14: =E13*ItemsPerTicket | F14: =F13*ItemsPerTicket | G14: =G13*ItemsPerTicket | H14: =H13*ItemsPerTicket | I14: =I13*ItemsPerTicket | J14: =J13*ItemsPerTicket | ... AL14: =AL13*ItemsPerTicket | AM14: =SUM(C14:N14) | AN14: =SUM(O14:Z14) | AO14: =SUM(AA14:AL14) | AP14: =SUM(AM14:AO14)
A15: Ingresos netos | B15: € | C15: =C14*WeightedNetPrice*(1+INDEX(ScenarioMatrix,3,$B$3))^(1-1) | D15: =D14*WeightedNetPrice*(1+INDEX(ScenarioMatrix,3,$B$3))^(1-1) | E15: =E14*WeightedNetPrice*(1+INDEX(ScenarioMatrix,3,$B$3))^(1-1) | F15: =F14*WeightedNetPrice*(1+INDEX(ScenarioMatrix,3,$B$3))^(1-1) | G15: =G14*WeightedNetPrice*(1+INDEX(ScenarioMatrix,3,$B$3))^(1-1) | H15: =H14*WeightedNetPrice*(1+INDEX(ScenarioMatrix,3,$B$3))^(1-1) | I15: =I14*WeightedNetPrice*(1+INDEX(ScenarioMatrix,3,$B$3))^(1-1) | J15: =J14*WeightedNetPrice*(1+INDEX(ScenarioMatrix,3,$B$3))^(1-1) | ... N15: =N14*WeightedNetPrice*(1+INDEX(ScenarioMatrix,3,$B$3))^(1-1) | O15: =O14*WeightedNetPrice*(1+INDEX(ScenarioMatrix,3,$B$3))^(2-1) | P15: =P14*WeightedNetPrice*(1+INDEX(ScenarioMatrix,3,$B$3))^(2-1) | Q15: =Q14*WeightedNetPrice*(1+INDEX(ScenarioMatrix,3,$B$3))^(2-1) | R15: =R14*WeightedNetPrice*(1+INDEX(ScenarioMatrix,3,$B$3))^(2-1) | S15: =S14*WeightedNetPrice*(1+INDEX(ScenarioMatrix,3,$B$3))^(2-1) | T15: =T14*WeightedNetPrice*(1+INDEX(ScenarioMatrix,3,$B$3))^(2-1) | U15: =U14*WeightedNetPrice*(1+INDEX(ScenarioMatrix,3,$B$3))^(2-1) | V15: =V14*WeightedNetPrice*(1+INDEX(ScenarioMatrix,3,$B$3))^(2-1) | ... Z15: =Z14*WeightedNetPrice*(1+INDEX(ScenarioMatrix,3,$B$3))^(2-1) | AA15: =AA14*WeightedNetPrice*(1+INDEX(ScenarioMatrix,3,$B$3))^(3-1) | AB15: =AB14*WeightedNetPrice*(1+INDEX(ScenarioMatrix,3,$B$3))^(3-1) | AC15: =AC14*WeightedNetPrice*(1+INDEX(ScenarioMatrix,3,$B$3))^(3-1) | AD15: =AD14*WeightedNetPrice*(1+INDEX(ScenarioMatrix,3,$B$3))^(3-1) | AE15: =AE14*WeightedNetPrice*(1+INDEX(ScenarioMatrix,3,$B$3))^(3-1) | AF15: =AF14*WeightedNetPrice*(1+INDEX(ScenarioMatrix,3,$B$3))^(3-1) | AG15: =AG14*WeightedNetPrice*(1+INDEX(ScenarioMatrix,3,$B$3))^(3-1) | AH15: =AH14*WeightedNetPrice*(1+INDEX(ScenarioMatrix,3,$B$3))^(3-1) | ... AL15: =AL14*WeightedNetPrice*(1+INDEX(ScenarioMatrix,3,$B$3))^(3-1) | AM15: =SUM(C15:N15) | AN15: =SUM(O15:Z15) | AO15: =SUM(AA15:AL15) | AP15: =SUM(AM15:AO15)
A16: COGS | B16: € | C16: =C14*WeightedCostAdj*(1+INDEX(ScenarioMatrix,4,$B$3))^(1-1) | D16: =D14*WeightedCostAdj*(1+INDEX(ScenarioMatrix,4,$B$3))^(1-1) | E16: =E14*WeightedCostAdj*(1+INDEX(ScenarioMatrix,4,$B$3))^(1-1) | F16: =F14*WeightedCostAdj*(1+INDEX(ScenarioMatrix,4,$B$3))^(1-1) | G16: =G14*WeightedCostAdj*(1+INDEX(ScenarioMatrix,4,$B$3))^(1-1) | H16: =H14*WeightedCostAdj*(1+INDEX(ScenarioMatrix,4,$B$3))^(1-1) | I16: =I14*WeightedCostAdj*(1+INDEX(ScenarioMatrix,4,$B$3))^(1-1) | J16: =J14*WeightedCostAdj*(1+INDEX(ScenarioMatrix,4,$B$3))^(1-1) | ... N16: =N14*WeightedCostAdj*(1+INDEX(ScenarioMatrix,4,$B$3))^(1-1) | O16: =O14*WeightedCostAdj*(1+INDEX(ScenarioMatrix,4,$B$3))^(2-1) | P16: =P14*WeightedCostAdj*(1+INDEX(ScenarioMatrix,4,$B$3))^(2-1) | Q16: =Q14*WeightedCostAdj*(1+INDEX(ScenarioMatrix,4,$B$3))^(2-1) | R16: =R14*WeightedCostAdj*(1+INDEX(ScenarioMatrix,4,$B$3))^(2-1) | S16: =S14*WeightedCostAdj*(1+INDEX(ScenarioMatrix,4,$B$3))^(2-1) | T16: =T14*WeightedCostAdj*(1+INDEX(ScenarioMatrix,4,$B$3))^(2-1) | U16: =U14*WeightedCostAdj*(1+INDEX(ScenarioMatrix,4,$B$3))^(2-1) | V16: =V14*WeightedCostAdj*(1+INDEX(ScenarioMatrix,4,$B$3))^(2-1) | ... Z16: =Z14*WeightedCostAdj*(1+INDEX(ScenarioMatrix,4,$B$3))^(2-1) | AA16: =AA14*WeightedCostAdj*(1+INDEX(ScenarioMatrix,4,$B$3))^(3-1) | AB16: =AB14*WeightedCostAdj*(1+INDEX(ScenarioMatrix,4,$B$3))^(3-1) | AC16: =AC14*WeightedCostAdj*(1+INDEX(ScenarioMatrix,4,$B$3))^(3-1) | AD16: =AD14*WeightedCostAdj*(1+INDEX(ScenarioMatrix,4,$B$3))^(3-1) | AE16: =AE14*WeightedCostAdj*(1+INDEX(ScenarioMatrix,4,$B$3))^(3-1) | AF16: =AF14*WeightedCostAdj*(1+INDEX(ScenarioMatrix,4,$B$3))^(3-1) | AG16: =AG14*WeightedCostAdj*(1+INDEX(ScenarioMatrix,4,$B$3))^(3-1) | AH16: =AH14*WeightedCostAdj*(1+INDEX(ScenarioMatrix,4,$B$3))^(3-1) | ... AL16: =AL14*WeightedCostAdj*(1+INDEX(ScenarioMatrix,4,$B$3))^(3-1) | AM16: =SUM(C16:N16) | AN16: =SUM(O16:Z16) | AO16: =SUM(AA16:AL16) | AP16: =SUM(AM16:AO16)
A17: Margen bruto | B17: € | C17: =C15-C16 | D17: =D15-D16 | E17: =E15-E16 | F17: =F15-F16 | G17: =G15-G16 | H17: =H15-H16 | I17: =I15-I16 | J17: =J15-J16 | ... AL17: =AL15-AL16 | AM17: =SUM(C17:N17) | AN17: =SUM(O17:Z17) | AO17: =SUM(AA17:AL17) | AP17: =SUM(AM17:AO17)
A18: Personal | B18: € | C18: =INDEX(StaffCostByYear,1,C7)*INDEX(ScenarioMatrix,5,$B$3)/12 | D18: =INDEX(StaffCostByYear,1,D7)*INDEX(ScenarioMatrix,5,$B$3)/12 | E18: =INDEX(StaffCostByYear,1,E7)*INDEX(ScenarioMatrix,5,$B$3)/12 | F18: =INDEX(StaffCostByYear,1,F7)*INDEX(ScenarioMatrix,5,$B$3)/12 | G18: =INDEX(StaffCostByYear,1,G7)*INDEX(ScenarioMatrix,5,$B$3)/12 | H18: =INDEX(StaffCostByYear,1,H7)*INDEX(ScenarioMatrix,5,$B$3)/12 | I18: =INDEX(StaffCostByYear,1,I7)*INDEX(ScenarioMatrix,5,$B$3)/12 | J18: =INDEX(StaffCostByYear,1,J7)*INDEX(ScenarioMatrix,5,$B$3)/12 | ... AL18: =INDEX(StaffCostByYear,1,AL7)*INDEX(ScenarioMatrix,5,$B$3)/12 | AM18: =SUM(C18:N18) | AN18: =SUM(O18:Z18) | AO18: =SUM(AA18:AL18) | AP18: =SUM(AM18:AO18)
A19: Alquiler | B19: € | C19: =RentMonth*INDEX(ScenarioMatrix,6,$B$3)*(1+RentGrowth)^(C7-1) | D19: =RentMonth*INDEX(ScenarioMatrix,6,$B$3)*(1+RentGrowth)^(D7-1) | E19: =RentMonth*INDEX(ScenarioMatrix,6,$B$3)*(1+RentGrowth)^(E7-1) | F19: =RentMonth*INDEX(ScenarioMatrix,6,$B$3)*(1+RentGrowth)^(F7-1) | G19: =RentMonth*INDEX(ScenarioMatrix,6,$B$3)*(1+RentGrowth)^(G7-1) | H19: =RentMonth*INDEX(ScenarioMatrix,6,$B$3)*(1+RentGrowth)^(H7-1) | I19: =RentMonth*INDEX(ScenarioMatrix,6,$B$3)*(1+RentGrowth)^(I7-1) | J19: =RentMonth*INDEX(ScenarioMatrix,6,$B$3)*(1+RentGrowth)^(J7-1) | ... AL19: =RentMonth*INDEX(ScenarioMatrix,6,$B$3)*(1+RentGrowth)^(AL7-1) | AM19: =SUM(C19:N19) | AN19: =SUM(O19:Z19) | AO19: =SUM(AA19:AL19) | AP19: =SUM(AM19:AO19)
A20: Suministros | B20: € | C20: =UtilitiesMonth*(1+INDEX(ScenarioMatrix,7,$B$3))^(C7-1) | D20: =UtilitiesMonth*(1+INDEX(ScenarioMatrix,7,$B$3))^(D7-1) | E20: =UtilitiesMonth*(1+INDEX(ScenarioMatrix,7,$B$3))^(E7-1) | F20: =UtilitiesMonth*(1+INDEX(ScenarioMatrix,7,$B$3))^(F7-1) | G20: =UtilitiesMonth*(1+INDEX(ScenarioMatrix,7,$B$3))^(G7-1) | H20: =UtilitiesMonth*(1+INDEX(ScenarioMatrix,7,$B$3))^(H7-1) | I20: =UtilitiesMonth*(1+INDEX(ScenarioMatrix,7,$B$3))^(I7-1) | J20: =UtilitiesMonth*(1+INDEX(ScenarioMatrix,7,$B$3))^(J7-1) | ... AL20: =UtilitiesMonth*(1+INDEX(ScenarioMatrix,7,$B$3))^(AL7-1) | AM20: =SUM(C20:N20) | AN20: =SUM(O20:Z20) | AO20: =SUM(AA20:AL20) | AP20: =SUM(AM20:AO20)
A21: Servicios fijos | B21: € | C21: =FixedServicesMonth*(1+INDEX(ScenarioMatrix,7,$B$3))^(C7-1) | D21: =FixedServicesMonth*(1+INDEX(ScenarioMatrix,7,$B$3))^(D7-1) | E21: =FixedServicesMonth*(1+INDEX(ScenarioMatrix,7,$B$3))^(E7-1) | F21: =FixedServicesMonth*(1+INDEX(ScenarioMatrix,7,$B$3))^(F7-1) | G21: =FixedServicesMonth*(1+INDEX(ScenarioMatrix,7,$B$3))^(G7-1) | H21: =FixedServicesMonth*(1+INDEX(ScenarioMatrix,7,$B$3))^(H7-1) | I21: =FixedServicesMonth*(1+INDEX(ScenarioMatrix,7,$B$3))^(I7-1) | J21: =FixedServicesMonth*(1+INDEX(ScenarioMatrix,7,$B$3))^(J7-1) | ... AL21: =FixedServicesMonth*(1+INDEX(ScenarioMatrix,7,$B$3))^(AL7-1) | AM21: =SUM(C21:N21) | AN21: =SUM(O21:Z21) | AO21: =SUM(AA21:AL21) | AP21: =SUM(AM21:AO21)
A22: Marketing fijo | B22: € | C22: =FixedMarketingMonth*(1+FixedMarketingGrowth)^(C7-1) | D22: =FixedMarketingMonth*(1+FixedMarketingGrowth)^(D7-1) | E22: =FixedMarketingMonth*(1+FixedMarketingGrowth)^(E7-1) | F22: =FixedMarketingMonth*(1+FixedMarketingGrowth)^(F7-1) | G22: =FixedMarketingMonth*(1+FixedMarketingGrowth)^(G7-1) | H22: =FixedMarketingMonth*(1+FixedMarketingGrowth)^(H7-1) | I22: =FixedMarketingMonth*(1+FixedMarketingGrowth)^(I7-1) | J22: =FixedMarketingMonth*(1+FixedMarketingGrowth)^(J7-1) | ... AL22: =FixedMarketingMonth*(1+FixedMarketingGrowth)^(AL7-1) | AM22: =SUM(C22:N22) | AN22: =SUM(O22:Z22) | AO22: =SUM(AA22:AL22) | AP22: =SUM(AM22:AO22)
A23: Marketing variable | B23: € | C23: =INDEX(ScenarioMatrix,8,$B$3)*C15 | D23: =INDEX(ScenarioMatrix,8,$B$3)*D15 | E23: =INDEX(ScenarioMatrix,8,$B$3)*E15 | F23: =INDEX(ScenarioMatrix,8,$B$3)*F15 | G23: =INDEX(ScenarioMatrix,8,$B$3)*G15 | H23: =INDEX(ScenarioMatrix,8,$B$3)*H15 | I23: =INDEX(ScenarioMatrix,8,$B$3)*I15 | J23: =INDEX(ScenarioMatrix,8,$B$3)*J15 | ... AL23: =INDEX(ScenarioMatrix,8,$B$3)*AL15 | AM23: =SUM(C23:N23) | AN23: =SUM(O23:Z23) | AO23: =SUM(AA23:AL23) | AP23: =SUM(AM23:AO23)
A24: Otros gastos | B24: € | C24: =OtherOpexMonth*INDEX(ScenarioMatrix,9,$B$3)*(1+INDEX(ScenarioMatrix,10,$B$3))^(C7-1) | D24: =OtherOpexMonth*INDEX(ScenarioMatrix,9,$B$3)*(1+INDEX(ScenarioMatrix,10,$B$3))^(D7-1) | E24: =OtherOpexMonth*INDEX(ScenarioMatrix,9,$B$3)*(1+INDEX(ScenarioMatrix,10,$B$3))^(E7-1) | F24: =OtherOpexMonth*INDEX(ScenarioMatrix,9,$B$3)*(1+INDEX(ScenarioMatrix,10,$B$3))^(F7-1) | G24: =OtherOpexMonth*INDEX(ScenarioMatrix,9,$B$3)*(1+INDEX(ScenarioMatrix,10,$B$3))^(G7-1) | H24: =OtherOpexMonth*INDEX(ScenarioMatrix,9,$B$3)*(1+INDEX(ScenarioMatrix,10,$B$3))^(H7-1) | I24: =OtherOpexMonth*INDEX(ScenarioMatrix,9,$B$3)*(1+INDEX(ScenarioMatrix,10,$B$3))^(I7-1) | J24: =OtherOpexMonth*INDEX(ScenarioMatrix,9,$B$3)*(1+INDEX(ScenarioMatrix,10,$B$3))^(J7-1) | ... AL24: =OtherOpexMonth*INDEX(ScenarioMatrix,9,$B$3)*(1+INDEX(ScenarioMatrix,10,$B$3))^(AL7-1) | AM24: =SUM(C24:N24) | AN24: =SUM(O24:Z24) | AO24: =SUM(AA24:AL24) | AP24: =SUM(AM24:AO24)
A25: Total opex + personal | B25: € | C25: =SUM(C18:C24) | D25: =SUM(D18:D24) | E25: =SUM(E18:E24) | F25: =SUM(F18:F24) | G25: =SUM(G18:G24) | H25: =SUM(H18:H24) | I25: =SUM(I18:I24) | J25: =SUM(J18:J24) | ... AL25: =SUM(AL18:AL24) | AM25: =SUM(C25:N25) | AN25: =SUM(O25:Z25) | AO25: =SUM(AA25:AL25) | AP25: =SUM(AM25:AO25)
A26: EBITDA | B26: € | C26: =C17-C25 | D26: =D17-D25 | E26: =E17-E25 | F26: =F17-F25 | G26: =G17-G25 | H26: =H17-H25 | I26: =I17-I25 | J26: =J17-J25 | ... AL26: =AL17-AL25 | AM26: =SUM(C26:N26) | AN26: =SUM(O26:Z26) | AO26: =SUM(AA26:AL26) | AP26: =SUM(AM26:AO26)
A27: Amortización | B27: € | C27: =MonthlyDepreciation | D27: =MonthlyDepreciation | E27: =MonthlyDepreciation | F27: =MonthlyDepreciation | G27: =MonthlyDepreciation | H27: =MonthlyDepreciation | I27: =MonthlyDepreciation | J27: =MonthlyDepreciation | ... AL27: =MonthlyDepreciation | AM27: =SUM(C27:N27) | AN27: =SUM(O27:Z27) | AO27: =SUM(AA27:AL27) | AP27: =SUM(AM27:AO27)
A28: EBIT | B28: € | C28: =C26-C27 | D28: =D26-D27 | E28: =E26-E27 | F28: =F26-F27 | G28: =G26-G27 | H28: =H26-H27 | I28: =I26-I27 | J28: =J26-J27 | ... AL28: =AL26-AL27 | AM28: =SUM(C28:N28) | AN28: =SUM(O28:Z28) | AO28: =SUM(AA28:AL28) | AP28: =SUM(AM28:AO28)
A29: Intereses | B29: € | C29: =C53 | D29: =D53 | E29: =E53 | F29: =F53 | G29: =G53 | H29: =H53 | I29: =I53 | J29: =J53 | ... AL29: =AL53 | AM29: =SUM(C29:N29) | AN29: =SUM(O29:Z29) | AO29: =SUM(AA29:AL29) | AP29: =SUM(AM29:AO29)
A30: EBT | B30: € | C30: =C28-C29 | D30: =D28-D29 | E30: =E28-E29 | F30: =F28-F29 | G30: =G28-G29 | H30: =H28-H29 | I30: =I28-I29 | J30: =J28-J29 | ... AL30: =AL28-AL29 | AM30: =SUM(C30:N30) | AN30: =SUM(O30:Z30) | AO30: =SUM(AA30:AL30) | AP30: =SUM(AM30:AO30)
A31: Impuestos | B31: € | C31: =IF(C7=1,$B$63/12,IF(C7=2,$C$63/12,$D$63/12)) | D31: =IF(D7=1,$B$63/12,IF(D7=2,$C$63/12,$D$63/12)) | E31: =IF(E7=1,$B$63/12,IF(E7=2,$C$63/12,$D$63/12)) | F31: =IF(F7=1,$B$63/12,IF(F7=2,$C$63/12,$D$63/12)) | G31: =IF(G7=1,$B$63/12,IF(G7=2,$C$63/12,$D$63/12)) | H31: =IF(H7=1,$B$63/12,IF(H7=2,$C$63/12,$D$63/12)) | I31: =IF(I7=1,$B$63/12,IF(I7=2,$C$63/12,$D$63/12)) | J31: =IF(J7=1,$B$63/12,IF(J7=2,$C$63/12,$D$63/12)) | ... AL31: =IF(AL7=1,$B$63/12,IF(AL7=2,$C$63/12,$D$63/12)) | AM31: =SUM(C31:N31) | AN31: =SUM(O31:Z31) | AO31: =SUM(AA31:AL31) | AP31: =SUM(AM31:AO31)
A32: Beneficio neto | B32: € | C32: =C30-C31 | D32: =D30-D31 | E32: =E30-E31 | F32: =F30-F31 | G32: =G30-G31 | H32: =H30-H31 | I32: =I30-I31 | J32: =J30-J31 | ... AL32: =AL30-AL31 | AM32: =SUM(C32:N32) | AN32: =SUM(O32:Z32) | AO32: =SUM(AA32:AL32) | AP32: =SUM(AM32:AO32)
A33: Margen bruto % | B33: % | C33: =IFERROR(C17/C15,0) | D33: =IFERROR(D17/D15,0) | E33: =IFERROR(E17/E15,0) | F33: =IFERROR(F17/F15,0) | G33: =IFERROR(G17/G15,0) | H33: =IFERROR(H17/H15,0) | I33: =IFERROR(I17/I15,0) | J33: =IFERROR(J17/J15,0) | ... AP33: =IFERROR(AP17/AP15,0)
A34: Margen EBITDA % | B34: % | C34: =IFERROR(C26/C15,0) | D34: =IFERROR(D26/D15,0) | E34: =IFERROR(E26/E15,0) | F34: =IFERROR(F26/F15,0) | G34: =IFERROR(G26/G15,0) | H34: =IFERROR(H26/H15,0) | I34: =IFERROR(I26/I15,0) | J34: =IFERROR(J26/J15,0) | ... AP34: =IFERROR(AP26/AP15,0)
A35: Margen neto % | B35: % | C35: =IFERROR(C32/C15,0) | D35: =IFERROR(D32/D15,0) | E35: =IFERROR(E32/E15,0) | F35: =IFERROR(F32/F15,0) | G35: =IFERROR(G32/G15,0) | H35: =IFERROR(H32/H15,0) | I35: =IFERROR(I32/I15,0) | J35: =IFERROR(J32/J15,0) | ... AP35: =IFERROR(AP32/AP15,0)
A36: Check P&L (debe ser 0) | B36: € | C36: =C17-C25-C26 | D36: =D17-D25-D26 | E36: =E17-E25-E26 | F36: =F17-F25-F26 | G36: =G17-G25-G26 | H36: =H17-H25-H26 | I36: =I17-I25-I26 | J36: =J17-J25-J26 | ... AO36: =AO17-AO25-AO26 | AP36: =SUM(AM36:AO36)
A37: CAJA
A38: Caja inicial | B38: € | C38: =OpeningCash | D38: =C48 | E38: =D48 | F38: =E48 | G38: =F48 | H38: =G48 | I38: =H48 | J38: =I48 | K38: =J48 | ... AL38: =AK48 | AM38: =N38 | AN38: =Z38 | AO38: =AL38 | AP38: =AO38
A39: Capital circulante | B39: € | C39: =C16*(InventoryDays-PayableDays)/365 | D39: =D16*(InventoryDays-PayableDays)/365 | E39: =E16*(InventoryDays-PayableDays)/365 | F39: =F16*(InventoryDays-PayableDays)/365 | G39: =G16*(InventoryDays-PayableDays)/365 | H39: =H16*(InventoryDays-PayableDays)/365 | I39: =I16*(InventoryDays-PayableDays)/365 | J39: =J16*(InventoryDays-PayableDays)/365 | ... AL39: =AL16*(InventoryDays-PayableDays)/365 | AM39: =N39 | AN39: =Z39 | AO39: =AL39 | AP39: =AO39
A40: Δ capital circulante | B40: € | C40: =C39-WC0 | D40: =D39-C39 | E40: =E39-D39 | F40: =F39-E39 | G40: =G39-F39 | H40: =H39-G39 | I40: =I39-H39 | J40: =J39-I39 | K40: =K39-J39 | ... AL40: =AL39-AK39 | AM40: =SUM(C40:N40) | AN40: =SUM(O40:Z40) | AO40: =SUM(AA40:AL40) | AP40: =SUM(AM40:AO40)
A41: Capex de mantenimiento | B41: € | C41: =C15*MaintenanceCapexPct | D41: =D15*MaintenanceCapexPct | E41: =E15*MaintenanceCapexPct | F41: =F15*MaintenanceCapexPct | G41: =G15*MaintenanceCapexPct | H41: =H15*MaintenanceCapexPct | I41: =I15*MaintenanceCapexPct | J41: =J15*MaintenanceCapexPct | ... AL41: =AL15*MaintenanceCapexPct | AM41: =SUM(C41:N41) | AN41: =SUM(O41:Z41) | AO41: =SUM(AA41:AL41) | AP41: =SUM(AM41:AO41)
A42: Impuesto teórico sin deuda | B42: € | C42: =IF(C7=1,$B$68/12,IF(C7=2,$C$68/12,$D$68/12)) | D42: =IF(D7=1,$B$68/12,IF(D7=2,$C$68/12,$D$68/12)) | E42: =IF(E7=1,$B$68/12,IF(E7=2,$C$68/12,$D$68/12)) | F42: =IF(F7=1,$B$68/12,IF(F7=2,$C$68/12,$D$68/12)) | G42: =IF(G7=1,$B$68/12,IF(G7=2,$C$68/12,$D$68/12)) | H42: =IF(H7=1,$B$68/12,IF(H7=2,$C$68/12,$D$68/12)) | I42: =IF(I7=1,$B$68/12,IF(I7=2,$C$68/12,$D$68/12)) | J42: =IF(J7=1,$B$68/12,IF(J7=2,$C$68/12,$D$68/12)) | ... AL42: =IF(AL7=1,$B$68/12,IF(AL7=2,$C$68/12,$D$68/12)) | AM42: =SUM(C42:N42) | AN42: =SUM(O42:Z42) | AO42: =SUM(AA42:AL42) | AP42: =SUM(AM42:AO42)
A43: FCFF | B43: € | C43: =C26-C42-C41-C40 | D43: =D26-D42-D41-D40 | E43: =E26-E42-E41-E40 | F43: =F26-F42-F41-F40 | G43: =G26-G42-G41-G40 | H43: =H26-H42-H41-H40 | I43: =I26-I42-I41-I40 | J43: =J26-J42-J41-J40 | ... AL43: =AL26-AL42-AL41-AL40 | AM43: =SUM(C43:N43) | AN43: =SUM(O43:Z43) | AO43: =SUM(AA43:AL43) | AP43: =SUM(AM43:AO43)
A44: Intereses | B44: € | C44: =C53 | D44: =D53 | E44: =E53 | F44: =F53 | G44: =G53 | H44: =H53 | I44: =I53 | J44: =J53 | ... AL44: =AL53 | AM44: =SUM(C44:N44) | AN44: =SUM(O44:Z44) | AO44: =SUM(AA44:AL44) | AP44: =SUM(AM44:AO44)
A45: Escudo fiscal | B45: € | C45: =C42-C31 | D45: =D42-D31 | E45: =E42-E31 | F45: =F42-F31 | G45: =G42-G31 | H45: =H42-H31 | I45: =I42-I31 | J45: =J42-J31 | ... AL45: =AL42-AL31 | AM45: =SUM(C45:N45) | AN45: =SUM(O45:Z45) | AO45: =SUM(AA45:AL45) | AP45: =SUM(AM45:AO45)
A46: Principal | B46: € | C46: =C54 | D46: =D54 | E46: =E54 | F46: =F54 | G46: =G54 | H46: =H54 | I46: =I54 | J46: =J54 | ... AL46: =AL54 | AM46: =SUM(C46:N46) | AN46: =SUM(O46:Z46) | AO46: =SUM(AA46:AL46) | AP46: =SUM(AM46:AO46)
A47: FCFE | B47: € | C47: =C43-C44+C45-C46 | D47: =D43-D44+D45-D46 | E47: =E43-E44+E45-E46 | F47: =F43-F44+F45-F46 | G47: =G43-G44+G45-G46 | H47: =H43-H44+H45-H46 | I47: =I43-I44+I45-I46 | J47: =J43-J44+J45-J46 | ... AL47: =AL43-AL44+AL45-AL46 | AM47: =SUM(C47:N47) | AN47: =SUM(O47:Z47) | AO47: =SUM(AA47:AL47) | AP47: =SUM(AM47:AO47)
A48: Caja final | B48: € | C48: =C38+C47 | D48: =D38+D47 | E48: =E38+E47 | F48: =F38+F47 | G48: =G38+G47 | H48: =H38+H47 | I48: =I38+I47 | J48: =J38+J47 | ... AL48: =AL38+AL47 | AM48: =N48 | AN48: =Z48 | AO48: =AL48 | AP48: =AO48
A49: Check caja mínima | B49: texto | C49: =IF(C48<MinCash,"Alerta","OK") | D49: =IF(D48<MinCash,"Alerta","OK") | E49: =IF(E48<MinCash,"Alerta","OK") | F49: =IF(F48<MinCash,"Alerta","OK") | G49: =IF(G48<MinCash,"Alerta","OK") | H49: =IF(H48<MinCash,"Alerta","OK") | I49: =IF(I48<MinCash,"Alerta","OK") | J49: =IF(J48<MinCash,"Alerta","OK") | ... AL49: =IF(AL48<MinCash,"Alerta","OK")
A50: Check caja (debe ser 0) | B50: € | C50: =C38+C47-C48 | D50: =D38+D47-D48 | E50: =E38+E47-E48 | F50: =F38+F47-F48 | G50: =G38+G47-G48 | H50: =H38+H47-H48 | I50: =I38+I47-I48 | J50: =J38+J47-J48 | ... AL50: =AL38+AL47-AL48 | AM50: =SUM(C50:N50) | AN50: =SUM(O50:Z50) | AO50: =SUM(AA50:AL50) | AP50: =SUM(AM50:AO50)
A51: CALENDARIO DE DEUDA
A52: Deuda inicial | B52: € | C52: =LoanAmount | D52: =C55 | E52: =D55 | F52: =E55 | G52: =F55 | H52: =G55 | I52: =H55 | J52: =I55 | K52: =J55 | ... AL52: =AK55 | AM52: =N52 | AN52: =Z52 | AO52: =AL52 | AP52: =AO52
A53: Intereses | B53: € | C53: =C52*LoanRate/12 | D53: =D52*LoanRate/12 | E53: =E52*LoanRate/12 | F53: =F52*LoanRate/12 | G53: =G52*LoanRate/12 | H53: =H52*LoanRate/12 | I53: =I52*LoanRate/12 | J53: =J52*LoanRate/12 | ... AL53: =AL52*LoanRate/12 | AM53: =SUM(C53:N53) | AN53: =SUM(O53:Z53) | AO53: =SUM(AA53:AL53) | AP53: =SUM(AM53:AO53)
A54: Principal | B54: € | C54: =MIN(LoanPayment-C53,C52) | D54: =MIN(LoanPayment-D53,D52) | E54: =MIN(LoanPayment-E53,E52) | F54: =MIN(LoanPayment-F53,F52) | G54: =MIN(LoanPayment-G53,G52) | H54: =MIN(LoanPayment-H53,H52) | I54: =MIN(LoanPayment-I53,I52) | J54: =MIN(LoanPayment-J53,J52) | ... AL54: =MIN(LoanPayment-AL53,AL52) | AM54: =SUM(C54:N54) | AN54: =SUM(O54:Z54) | AO54: =SUM(AA54:AL54) | AP54: =SUM(AM54:AO54)
A55: Deuda final | B55: € | C55: =C52-C54 | D55: =D52-D54 | E55: =E52-E54 | F55: =F52-F54 | G55: =G52-G54 | H55: =H52-H54 | I55: =I52-I54 | J55: =J52-J54 | ... AL55: =AL52-AL54 | AM55: =N55 | AN55: =Z55 | AO55: =AL55 | AP55: =AO55
A56: Cuota | B56: € | C56: =LoanPayment | D56: =LoanPayment | E56: =LoanPayment | F56: =LoanPayment | G56: =LoanPayment | H56: =LoanPayment | I56: =LoanPayment | J56: =LoanPayment | ... AL56: =LoanPayment | AM56: =SUM(C56:N56) | AN56: =SUM(O56:Z56) | AO56: =SUM(AA56:AL56) | AP56: =SUM(AM56:AO56)
A57: DSCR | B57: × | C57: =IFERROR((C26-C31)/(C53+C54),0) | D57: =IFERROR((D26-D31)/(D53+D54),0) | E57: =IFERROR((E26-E31)/(E53+E54),0) | F57: =IFERROR((F26-F31)/(F53+F54),0) | G57: =IFERROR((G26-G31)/(G53+G54),0) | H57: =IFERROR((H26-H31)/(H53+H54),0) | I57: =IFERROR((I26-I31)/(I53+I54),0) | J57: =IFERROR((J26-J31)/(J53+J54),0) | ... AP57: =IFERROR((AP26-AP31)/(AP53+AP54),0)
A58: IMPUESTO ANUAL Y PÉRDIDAS COMPENSABLES
A59: Concepto | B59: 2026 | C59: 2027 | D59: 2028 | E59: La cuota mensual de la fila 31 es la cuota anual / 12.
A60: EBT anual | B60: =AM30 | C60: =AN30 | D60: =AO30
A61: Pérdidas inicio (con deuda) | B61: 0 | C61: =B64 | D61: =C64
A62: Base imponible | B62: =MAX(0,B60-B61) | C62: =MAX(0,C60-C61) | D62: =MAX(0,D60-D61)
A63: Cuota | B63: =B62*TaxRate | C63: =C62*TaxRate | D63: =D62*TaxRate
A64: Pérdidas fin | B64: =B61-MIN(B61,MAX(0,B60))+MAX(0,-B60) | C64: =C61-MIN(C61,MAX(0,C60))+MAX(0,-C60) | D64: =D61-MIN(D61,MAX(0,D60))+MAX(0,-D60)
A65: EBIT anual | B65: =AM28 | C65: =AN28 | D65: =AO28
A66: Pérdidas inicio (sin deuda) | B66: 0 | C66: =B69 | D66: =C69
A67: Base imponible sin deuda | B67: =MAX(0,B65-B66) | C67: =MAX(0,C65-C66) | D67: =MAX(0,D65-D66)
A68: Cuota sin deuda | B68: =B67*TaxRate | C68: =C67*TaxRate | D68: =D67*TaxRate
A69: Pérdidas fin (sin deuda) | B69: =B66-MIN(B66,MAX(0,B65))+MAX(0,-B65) | C69: =C66-MIN(C66,MAX(0,C65))+MAX(0,-C65) | D69: =D66-MIN(D66,MAX(0,D65))+MAX(0,-D65)
A70: Escudo fiscal | B70: =B68-B63 | C70: =C68-C63 | D70: =D68-D63
A74: RESUMEN ANUAL
A75: Métrica | B75: 2026 | C75: 2027 | D75: 2028 | E75: 3 años
A76: Ingresos netos | B76: =AM15 | C76: =AN15 | D76: =AO15 | E76: =SUM(B76:D76)
A77: COGS | B77: =AM16 | C77: =AN16 | D77: =AO16 | E77: =SUM(B77:D77)
A78: Margen bruto | B78: =AM17 | C78: =AN17 | D78: =AO17 | E78: =SUM(B78:D78)
A79: Personal | B79: =AM18 | C79: =AN18 | D79: =AO18 | E79: =SUM(B79:D79)
A80: Alquiler | B80: =AM19 | C80: =AN19 | D80: =AO19 | E80: =SUM(B80:D80)
A81: Suministros | B81: =AM20 | C81: =AN20 | D81: =AO20 | E81: =SUM(B81:D81)
A82: Servicios fijos | B82: =AM21 | C82: =AN21 | D82: =AO21 | E82: =SUM(B82:D82)
A83: Marketing fijo | B83: =AM22 | C83: =AN22 | D83: =AO22 | E83: =SUM(B83:D83)
A84: Marketing variable | B84: =AM23 | C84: =AN23 | D84: =AO23 | E84: =SUM(B84:D84)
A85: Otros gastos | B85: =AM24 | C85: =AN24 | D85: =AO24 | E85: =SUM(B85:D85)
A86: EBITDA | B86: =AM26 | C86: =AN26 | D86: =AO26 | E86: =SUM(B86:D86)
A87: Amortización | B87: =AM27 | C87: =AN27 | D87: =AO27 | E87: =SUM(B87:D87)
A88: EBIT | B88: =AM28 | C88: =AN28 | D88: =AO28 | E88: =SUM(B88:D88)
A89: Intereses | B89: =AM29 | C89: =AN29 | D89: =AO29 | E89: =SUM(B89:D89)
A90: EBT | B90: =AM30 | C90: =AN30 | D90: =AO30 | E90: =SUM(B90:D90)
A91: Impuestos | B91: =AM31 | C91: =AN31 | D91: =AO31 | E91: =SUM(B91:D91)
A92: Beneficio neto | B92: =AM32 | C92: =AN32 | D92: =AO32 | E92: =SUM(B92:D92)
A93: CFO | B93: =B92+B87-AM40 | C93: =C92+C87-AN40 | D93: =D92+D87-AO40 | E93: =SUM(B93:D93)
A94: Capex mantenimiento | B94: =AM41 | C94: =AN41 | D94: =AO41 | E94: =SUM(B94:D94)
A95: FCFF | B95: =AM43 | C95: =AN43 | D95: =AO43 | E95: =SUM(B95:D95)
A96: Principal | B96: =AM46 | C96: =AN46 | D96: =AO46 | E96: =SUM(B96:D96)
A97: FCFE | B97: =AM47 | C97: =AN47 | D97: =AO47 | E97: =SUM(B97:D97)
A98: Caja final | B98: =N48 | C98: =Z48 | D98: =AL48 | E98: =D98
A99: Tickets/día | B99: =AM13/AM9 | C99: =AN13/AN9 | D99: =AO13/AO9 | E99: =SUM(B99:D99)/3
A100: Ticket medio neto | B100: =B76/AM13 | C100: =C76/AN13 | D100: =D76/AO13 | E100: =E76/SUM(AM13:AO13)
A101: Ticket medio con IVA | B101: =B100*1.1 | C101: =C100*1.1 | D101: =D100*1.1 | E101: =E100*1.1
A102: Punto de equilibrio EBITDA | B102: =(B79+B80+B81+B82+B83+B85)/((B76-B77-B84)/AM13)/AM9 | C102: =(C79+C80+C81+C82+C83+C85)/((C76-C77-C84)/AN13)/AN9 | D102: =(D79+D80+D81+D82+D83+D85)/((D76-D77-D84)/AO13)/AO9
A103: Punto de equilibrio total | B103: =(B79+B80+B81+B82+B83+B85+B87+B89)/((B76-B77-B84)/AM13)/AM9 | C103: =(C79+C80+C81+C82+C83+C85+C87+C89)/((C76-C77-C84)/AN13)/AN9 | D103: =(D79+D80+D81+D82+D83+D85+D87+D89)/((D76-D77-D84)/AO13)/AO9
A104: Margen de seguridad | B104: =(B99-B103)/B99 | C104: =(C99-C103)/C99 | D104: =(D99-D103)/D99
...

Sheet Base
A1: Cafetería Aurora — Escenario Base
A2: EUR, sin IVA. Solo se editan las hojas de entrada.
A3: Selector (1/2/3): | B3: 2 | C3: 1 = Pesimista · 2 = Base · 3 = Optimista
A4: Escenario: | B4: =CHOOSE(B3,"Pesimista","Base","Optimista") | C4: Cambia el selector para ver el mismo modelo con los supuestos de otro escenario.
A5: Índice de mes | B5: mes | C5: 1 | D5: =C5+1 | E5: =D5+1 | F5: =E5+1 | G5: =F5+1 | H5: =G5+1 | I5: =H5+1 | J5: =I5+1 | K5: =J5+1 | ... AL5: =AK5+1
A6: Fecha | B6: fecha | C6: =DATE(2026,1,1) | D6: =EDATE(C6,1) | E6: =EDATE(D6,1) | F6: =EDATE(E6,1) | G6: =EDATE(F6,1) | H6: =EDATE(G6,1) | I6: =EDATE(H6,1) | J6: =EDATE(I6,1) | K6: =EDATE(J6,1) | ... AL6: =EDATE(AK6,1)
A7: Año | B7: 1–3 | C7: =ROUNDUP(C5/12,0) | D7: =ROUNDUP(D5/12,0) | E7: =ROUNDUP(E5/12,0) | F7: =ROUNDUP(F5/12,0) | G7: =ROUNDUP(G5/12,0) | H7: =ROUNDUP(H5/12,0) | I7: =ROUNDUP(I5/12,0) | J7: =ROUNDUP(J5/12,0) | ... AL7: =ROUNDUP(AL5/12,0)
A8: Mes | B8: 1–12 | C8: =MOD(C5-1,12)+1 | D8: =MOD(D5-1,12)+1 | E8: =MOD(E5-1,12)+1 | F8: =MOD(F5-1,12)+1 | G8: =MOD(G5-1,12)+1 | H8: =MOD(H5-1,12)+1 | I8: =MOD(I5-1,12)+1 | J8: =MOD(J5-1,12)+1 | ... AL8: =MOD(AL5-1,12)+1
A9: Días operativos | B9: días | C9: =INDEX(OpeningDays,1,C8) | D9: =INDEX(OpeningDays,1,D8) | E9: =INDEX(OpeningDays,1,E8) | F9: =INDEX(OpeningDays,1,F8) | G9: =INDEX(OpeningDays,1,G8) | H9: =INDEX(OpeningDays,1,H8) | I9: =INDEX(OpeningDays,1,I8) | J9: =INDEX(OpeningDays,1,J8) | ... AL9: =INDEX(OpeningDays,1,AL8) | AM9: =SUM(C9:N9) | AN9: =SUM(O9:Z9) | AO9: =SUM(AA9:AL9) | AP9: =SUM(AM9:AO9)
A11: CUENTA DE RESULTADOS
A12: Tickets/día | B12: tickets/día | C12: =BaseTicketsDay*INDEX(ScenarioMatrix,1,$B$3)*(1+INDEX(ScenarioMatrix,2,$B$3))^(1-1)*INDEX(Seasonality,1,C8)*IF(1=1,INDEX(Ramp,1,C8),1) | D12: =BaseTicketsDay*INDEX(ScenarioMatrix,1,$B$3)*(1+INDEX(ScenarioMatrix,2,$B$3))^(1-1)*INDEX(Seasonality,1,D8)*IF(1=1,INDEX(Ramp,1,D8),1) | E12: =BaseTicketsDay*INDEX(ScenarioMatrix,1,$B$3)*(1+INDEX(ScenarioMatrix,2,$B$3))^(1-1)*INDEX(Seasonality,1,E8)*IF(1=1,INDEX(Ramp,1,E8),1) | F12: =BaseTicketsDay*INDEX(ScenarioMatrix,1,$B$3)*(1+INDEX(ScenarioMatrix,2,$B$3))^(1-1)*INDEX(Seasonality,1,F8)*IF(1=1,INDEX(Ramp,1,F8),1) | G12: =BaseTicketsDay*INDEX(ScenarioMatrix,1,$B$3)*(1+INDEX(ScenarioMatrix,2,$B$3))^(1-1)*INDEX(Seasonality,1,G8)*IF(1=1,INDEX(Ramp,1,G8),1) | H12: =BaseTicketsDay*INDEX(ScenarioMatrix,1,$B$3)*(1+INDEX(ScenarioMatrix,2,$B$3))^(1-1)*INDEX(Seasonality,1,H8)*IF(1=1,INDEX(Ramp,1,H8),1) | I12: =BaseTicketsDay*INDEX(ScenarioMatrix,1,$B$3)*(1+INDEX(ScenarioMatrix,2,$B$3))^(1-1)*INDEX(Seasonality,1,I8)*IF(1=1,INDEX(Ramp,1,I8),1) | J12: =BaseTicketsDay*INDEX(ScenarioMatrix,1,$B$3)*(1+INDEX(ScenarioMatrix,2,$B$3))^(1-1)*INDEX(Seasonality,1,J8)*IF(1=1,INDEX(Ramp,1,J8),1) | ... N12: =BaseTicketsDay*INDEX(ScenarioMatrix,1,$B$3)*(1+INDEX(ScenarioMatrix,2,$B$3))^(1-1)*INDEX(Seasonality,1,N8)*IF(1=1,INDEX(Ramp,1,N8),1) | O12: =BaseTicketsDay*INDEX(ScenarioMatrix,1,$B$3)*(1+INDEX(ScenarioMatrix,2,$B$3))^(2-1)*INDEX(Seasonality,1,O8)*IF(2=1,INDEX(Ramp,1,O8),1) | P12: =BaseTicketsDay*INDEX(ScenarioMatrix,1,$B$3)*(1+INDEX(ScenarioMatrix,2,$B$3))^(2-1)*INDEX(Seasonality,1,P8)*IF(2=1,INDEX(Ramp,1,P8),1) | Q12: =BaseTicketsDay*INDEX(ScenarioMatrix,1,$B$3)*(1+INDEX(ScenarioMatrix,2,$B$3))^(2-1)*INDEX(Seasonality,1,Q8)*IF(2=1,INDEX(Ramp,1,Q8),1) | R12: =BaseTicketsDay*INDEX(ScenarioMatrix,1,$B$3)*(1+INDEX(ScenarioMatrix,2,$B$3))^(2-1)*INDEX(Seasonality,1,R8)*IF(2=1,INDEX(Ramp,1,R8),1) | S12: =BaseTicketsDay*INDEX(ScenarioMatrix,1,$B$3)*(1+INDEX(ScenarioMatrix,2,$B$3))^(2-1)*INDEX(Seasonality,1,S8)*IF(2=1,INDEX(Ramp,1,S8),1) | T12: =BaseTicketsDay*INDEX(ScenarioMatrix,1,$B$3)*(1+INDEX(ScenarioMatrix,2,$B$3))^(2-1)*INDEX(Seasonality,1,T8)*IF(2=1,INDEX(Ramp,1,T8),1) | U12: =BaseTicketsDay*INDEX(ScenarioMatrix,1,$B$3)*(1+INDEX(ScenarioMatrix,2,$B$3))^(2-1)*INDEX(Seasonality,1,U8)*IF(2=1,INDEX(Ramp,1,U8),1) | V12: =BaseTicketsDay*INDEX(ScenarioMatrix,1,$B$3)*(1+INDEX(ScenarioMatrix,2,$B$3))^(2-1)*INDEX(Seasonality,1,V8)*IF(2=1,INDEX(Ramp,1,V8),1) | ... Z12: =BaseTicketsDay*INDEX(ScenarioMatrix,1,$B$3)*(1+INDEX(ScenarioMatrix,2,$B$3))^(2-1)*INDEX(Seasonality,1,Z8)*IF(2=1,INDEX(Ramp,1,Z8),1) | AA12: =BaseTicketsDay*INDEX(ScenarioMatrix,1,$B$3)*(1+INDEX(ScenarioMatrix,2,$B$3))^(3-1)*INDEX(Seasonality,1,AA8)*IF(3=1,INDEX(Ramp,1,AA8),1) | AB12: =BaseTicketsDay*INDEX(ScenarioMatrix,1,$B$3)*(1+INDEX(ScenarioMatrix,2,$B$3))^(3-1)*INDEX(Seasonality,1,AB8)*IF(3=1,INDEX(Ramp,1,AB8),1) | AC12: =BaseTicketsDay*INDEX(ScenarioMatrix,1,$B$3)*(1+INDEX(ScenarioMatrix,2,$B$3))^(3-1)*INDEX(Seasonality,1,AC8)*IF(3=1,INDEX(Ramp,1,AC8),1) | AD12: =BaseTicketsDay*INDEX(ScenarioMatrix,1,$B$3)*(1+INDEX(ScenarioMatrix,2,$B$3))^(3-1)*INDEX(Seasonality,1,AD8)*IF(3=1,INDEX(Ramp,1,AD8),1) | AE12: =BaseTicketsDay*INDEX(ScenarioMatrix,1,$B$3)*(1+INDEX(ScenarioMatrix,2,$B$3))^(3-1)*INDEX(Seasonality,1,AE8)*IF(3=1,INDEX(Ramp,1,AE8),1) | AF12: =BaseTicketsDay*INDEX(ScenarioMatrix,1,$B$3)*(1+INDEX(ScenarioMatrix,2,$B$3))^(3-1)*INDEX(Seasonality,1,AF8)*IF(3=1,INDEX(Ramp,1,AF8),1) | AG12: =BaseTicketsDay*INDEX(ScenarioMatrix,1,$B$3)*(1+INDEX(ScenarioMatrix,2,$B$3))^(3-1)*INDEX(Seasonality,1,AG8)*IF(3=1,INDEX(Ramp,1,AG8),1) | AH12: =BaseTicketsDay*INDEX(ScenarioMatrix,1,$B$3)*(1+INDEX(ScenarioMatrix,2,$B$3))^(3-1)*INDEX(Seasonality,1,AH8)*IF(3=1,INDEX(Ramp,1,AH8),1) | ... AL12: =BaseTicketsDay*INDEX(ScenarioMatrix,1,$B$3)*(1+INDEX(ScenarioMatrix,2,$B$3))^(3-1)*INDEX(Seasonality,1,AL8)*IF(3=1,INDEX(Ramp,1,AL8),1) | AM12: =SUM(C12:N12) | AN12: =SUM(O12:Z12) | AO12: =SUM(AA12:AL12) | AP12: =SUM(AM12:AO12)
A13: Tickets | B13: tickets | C13: =C12*C9 | D13: =D12*D9 | E13: =E12*E9 | F13: =F12*F9 | G13: =G12*G9 | H13: =H12*H9 | I13: =I12*I9 | J13: =J12*J9 | ... AL13: =AL12*AL9 | AM13: =SUM(C13:N13) | AN13: =SUM(O13:Z13) | AO13: =SUM(AA13:AL13) | AP13: =SUM(AM13:AO13)
A14: Ítems vendidos | B14: ítems | C14: =C13*ItemsPerTicket | D14: =D13*ItemsPerTicket | E14: =E13*ItemsPerTicket | F14: =F13*ItemsPerTicket | G14: =G13*ItemsPerTicket | H14: =H13*ItemsPerTicket | I14: =I13*ItemsPerTicket | J14: =J13*ItemsPerTicket | ... AL14: =AL13*ItemsPerTicket | AM14: =SUM(C14:N14) | AN14: =SUM(O14:Z14) | AO14: =SUM(AA14:AL14) | AP14: =SUM(AM14:AO14)
A15: Ingresos netos | B15: € | C15: =C14*WeightedNetPrice*(1+INDEX(ScenarioMatrix,3,$B$3))^(1-1) | D15: =D14*WeightedNetPrice*(1+INDEX(ScenarioMatrix,3,$B$3))^(1-1) | E15: =E14*WeightedNetPrice*(1+INDEX(ScenarioMatrix,3,$B$3))^(1-1) | F15: =F14*WeightedNetPrice*(1+INDEX(ScenarioMatrix,3,$B$3))^(1-1) | G15: =G14*WeightedNetPrice*(1+INDEX(ScenarioMatrix,3,$B$3))^(1-1) | H15: =H14*WeightedNetPrice*(1+INDEX(ScenarioMatrix,3,$B$3))^(1-1) | I15: =I14*WeightedNetPrice*(1+INDEX(ScenarioMatrix,3,$B$3))^(1-1) | J15: =J14*WeightedNetPrice*(1+INDEX(ScenarioMatrix,3,$B$3))^(1-1) | ... N15: =N14*WeightedNetPrice*(1+INDEX(ScenarioMatrix,3,$B$3))^(1-1) | O15: =O14*WeightedNetPrice*(1+INDEX(ScenarioMatrix,3,$B$3))^(2-1) | P15: =P14*WeightedNetPrice*(1+INDEX(ScenarioMatrix,3,$B$3))^(2-1) | Q15: =Q14*WeightedNetPrice*(1+INDEX(ScenarioMatrix,3,$B$3))^(2-1) | R15: =R14*WeightedNetPrice*(1+INDEX(ScenarioMatrix,3,$B$3))^(2-1) | S15: =S14*WeightedNetPrice*(1+INDEX(ScenarioMatrix,3,$B$3))^(2-1) | T15: =T14*WeightedNetPrice*(1+INDEX(ScenarioMatrix,3,$B$3))^(2-1) | U15: =U14*WeightedNetPrice*(1+INDEX(ScenarioMatrix,3,$B$3))^(2-1) | V15: =V14*WeightedNetPrice*(1+INDEX(ScenarioMatrix,3,$B$3))^(2-1) | ... Z15: =Z14*WeightedNetPrice*(1+INDEX(ScenarioMatrix,3,$B$3))^(2-1) | AA15: =AA14*WeightedNetPrice*(1+INDEX(ScenarioMatrix,3,$B$3))^(3-1) | AB15: =AB14*WeightedNetPrice*(1+INDEX(ScenarioMatrix,3,$B$3))^(3-1) | AC15: =AC14*WeightedNetPrice*(1+INDEX(ScenarioMatrix,3,$B$3))^(3-1) | AD15: =AD14*WeightedNetPrice*(1+INDEX(ScenarioMatrix,3,$B$3))^(3-1) | AE15: =AE14*WeightedNetPrice*(1+INDEX(ScenarioMatrix,3,$B$3))^(3-1) | AF15: =AF14*WeightedNetPrice*(1+INDEX(ScenarioMatrix,3,$B$3))^(3-1) | AG15: =AG14*WeightedNetPrice*(1+INDEX(ScenarioMatrix,3,$B$3))^(3-1) | AH15: =AH14*WeightedNetPrice*(1+INDEX(ScenarioMatrix,3,$B$3))^(3-1) | ... AL15: =AL14*WeightedNetPrice*(1+INDEX(ScenarioMatrix,3,$B$3))^(3-1) | AM15: =SUM(C15:N15) | AN15: =SUM(O15:Z15) | AO15: =SUM(AA15:AL15) | AP15: =SUM(AM15:AO15)
A16: COGS | B16: € | C16: =C14*WeightedCostAdj*(1+INDEX(ScenarioMatrix,4,$B$3))^(1-1) | D16: =D14*WeightedCostAdj*(1+INDEX(ScenarioMatrix,4,$B$3))^(1-1) | E16: =E14*WeightedCostAdj*(1+INDEX(ScenarioMatrix,4,$B$3))^(1-1) | F16: =F14*WeightedCostAdj*(1+INDEX(ScenarioMatrix,4,$B$3))^(1-1) | G16: =G14*WeightedCostAdj*(1+INDEX(ScenarioMatrix,4,$B$3))^(1-1) | H16: =H14*WeightedCostAdj*(1+INDEX(ScenarioMatrix,4,$B$3))^(1-1) | I16: =I14*WeightedCostAdj*(1+INDEX(ScenarioMatrix,4,$B$3))^(1-1) | J16: =J14*WeightedCostAdj*(1+INDEX(ScenarioMatrix,4,$B$3))^(1-1) | ... N16: =N14*WeightedCostAdj*(1+INDEX(ScenarioMatrix,4,$B$3))^(1-1) | O16: =O14*WeightedCostAdj*(1+INDEX(ScenarioMatrix,4,$B$3))^(2-1) | P16: =P14*WeightedCostAdj*(1+INDEX(ScenarioMatrix,4,$B$3))^(2-1) | Q16: =Q14*WeightedCostAdj*(1+INDEX(ScenarioMatrix,4,$B$3))^(2-1) | R16: =R14*WeightedCostAdj*(1+INDEX(ScenarioMatrix,4,$B$3))^(2-1) | S16: =S14*WeightedCostAdj*(1+INDEX(ScenarioMatrix,4,$B$3))^(2-1) | T16: =T14*WeightedCostAdj*(1+INDEX(ScenarioMatrix,4,$B$3))^(2-1) | U16: =U14*WeightedCostAdj*(1+INDEX(ScenarioMatrix,4,$B$3))^(2-1) | V16: =V14*WeightedCostAdj*(1+INDEX(ScenarioMatrix,4,$B$3))^(2-1) | ... Z16: =Z14*WeightedCostAdj*(1+INDEX(ScenarioMatrix,4,$B$3))^(2-1) | AA16: =AA14*WeightedCostAdj*(1+INDEX(ScenarioMatrix,4,$B$3))^(3-1) | AB16: =AB14*WeightedCostAdj*(1+INDEX(ScenarioMatrix,4,$B$3))^(3-1) | AC16: =AC14*WeightedCostAdj*(1+INDEX(ScenarioMatrix,4,$B$3))^(3-1) | AD16: =AD14*WeightedCostAdj*(1+INDEX(ScenarioMatrix,4,$B$3))^(3-1) | AE16: =AE14*WeightedCostAdj*(1+INDEX(ScenarioMatrix,4,$B$3))^(3-1) | AF16: =AF14*WeightedCostAdj*(1+INDEX(ScenarioMatrix,4,$B$3))^(3-1) | AG16: =AG14*WeightedCostAdj*(1+INDEX(ScenarioMatrix,4,$B$3))^(3-1) | AH16: =AH14*WeightedCostAdj*(1+INDEX(ScenarioMatrix,4,$B$3))^(3-1) | ... AL16: =AL14*WeightedCostAdj*(1+INDEX(ScenarioMatrix,4,$B$3))^(3-1) | AM16: =SUM(C16:N16) | AN16: =SUM(O16:Z16) | AO16: =SUM(AA16:AL16) | AP16: =SUM(AM16:AO16)
A17: Margen bruto | B17: € | C17: =C15-C16 | D17: =D15-D16 | E17: =E15-E16 | F17: =F15-F16 | G17: =G15-G16 | H17: =H15-H16 | I17: =I15-I16 | J17: =J15-J16 | ... AL17: =AL15-AL16 | AM17: =SUM(C17:N17) | AN17: =SUM(O17:Z17) | AO17: =SUM(AA17:AL17) | AP17: =SUM(AM17:AO17)
A18: Personal | B18: € | C18: =INDEX(StaffCostByYear,1,C7)*INDEX(ScenarioMatrix,5,$B$3)/12 | D18: =INDEX(StaffCostByYear,1,D7)*INDEX(ScenarioMatrix,5,$B$3)/12 | E18: =INDEX(StaffCostByYear,1,E7)*INDEX(ScenarioMatrix,5,$B$3)/12 | F18: =INDEX(StaffCostByYear,1,F7)*INDEX(ScenarioMatrix,5,$B$3)/12 | G18: =INDEX(StaffCostByYear,1,G7)*INDEX(ScenarioMatrix,5,$B$3)/12 | H18: =INDEX(StaffCostByYear,1,H7)*INDEX(ScenarioMatrix,5,$B$3)/12 | I18: =INDEX(StaffCostByYear,1,I7)*INDEX(ScenarioMatrix,5,$B$3)/12 | J18: =INDEX(StaffCostByYear,1,J7)*INDEX(ScenarioMatrix,5,$B$3)/12 | ... AL18: =INDEX(StaffCostByYear,1,AL7)*INDEX(ScenarioMatrix,5,$B$3)/12 | AM18: =SUM(C18:N18) | AN18: =SUM(O18:Z18) | AO18: =SUM(AA18:AL18) | AP18: =SUM(AM18:AO18)
A19: Alquiler | B19: € | C19: =RentMonth*INDEX(ScenarioMatrix,6,$B$3)*(1+RentGrowth)^(C7-1) | D19: =RentMonth*INDEX(ScenarioMatrix,6,$B$3)*(1+RentGrowth)^(D7-1) | E19: =RentMonth*INDEX(ScenarioMatrix,6,$B$3)*(1+RentGrowth)^(E7-1) | F19: =RentMonth*INDEX(ScenarioMatrix,6,$B$3)*(1+RentGrowth)^(F7-1) | G19: =RentMonth*INDEX(ScenarioMatrix,6,$B$3)*(1+RentGrowth)^(G7-1) | H19: =RentMonth*INDEX(ScenarioMatrix,6,$B$3)*(1+RentGrowth)^(H7-1) | I19: =RentMonth*INDEX(ScenarioMatrix,6,$B$3)*(1+RentGrowth)^(I7-1) | J19: =RentMonth*INDEX(ScenarioMatrix,6,$B$3)*(1+RentGrowth)^(J7-1) | ... AL19: =RentMonth*INDEX(ScenarioMatrix,6,$B$3)*(1+RentGrowth)^(AL7-1) | AM19: =SUM(C19:N19) | AN19: =SUM(O19:Z19) | AO19: =SUM(AA19:AL19) | AP19: =SUM(AM19:AO19)
A20: Suministros | B20: € | C20: =UtilitiesMonth*(1+INDEX(ScenarioMatrix,7,$B$3))^(C7-1) | D20: =UtilitiesMonth*(1+INDEX(ScenarioMatrix,7,$B$3))^(D7-1) | E20: =UtilitiesMonth*(1+INDEX(ScenarioMatrix,7,$B$3))^(E7-1) | F20: =UtilitiesMonth*(1+INDEX(ScenarioMatrix,7,$B$3))^(F7-1) | G20: =UtilitiesMonth*(1+INDEX(ScenarioMatrix,7,$B$3))^(G7-1) | H20: =UtilitiesMonth*(1+INDEX(ScenarioMatrix,7,$B$3))^(H7-1) | I20: =UtilitiesMonth*(1+INDEX(ScenarioMatrix,7,$B$3))^(I7-1) | J20: =UtilitiesMonth*(1+INDEX(ScenarioMatrix,7,$B$3))^(J7-1) | ... AL20: =UtilitiesMonth*(1+INDEX(ScenarioMatrix,7,$B$3))^(AL7-1) | AM20: =SUM(C20:N20) | AN20: =SUM(O20:Z20) | AO20: =SUM(AA20:AL20) | AP20: =SUM(AM20:AO20)
A21: Servicios fijos | B21: € | C21: =FixedServicesMonth*(1+INDEX(ScenarioMatrix,7,$B$3))^(C7-1) | D21: =FixedServicesMonth*(1+INDEX(ScenarioMatrix,7,$B$3))^(D7-1) | E21: =FixedServicesMonth*(1+INDEX(ScenarioMatrix,7,$B$3))^(E7-1) | F21: =FixedServicesMonth*(1+INDEX(ScenarioMatrix,7,$B$3))^(F7-1) | G21: =FixedServicesMonth*(1+INDEX(ScenarioMatrix,7,$B$3))^(G7-1) | H21: =FixedServicesMonth*(1+INDEX(ScenarioMatrix,7,$B$3))^(H7-1) | I21: =FixedServicesMonth*(1+INDEX(ScenarioMatrix,7,$B$3))^(I7-1) | J21: =FixedServicesMonth*(1+INDEX(ScenarioMatrix,7,$B$3))^(J7-1) | ... AL21: =FixedServicesMonth*(1+INDEX(ScenarioMatrix,7,$B$3))^(AL7-1) | AM21: =SUM(C21:N21) | AN21: =SUM(O21:Z21) | AO21: =SUM(AA21:AL21) | AP21: =SUM(AM21:AO21)
A22: Marketing fijo | B22: € | C22: =FixedMarketingMonth*(1+FixedMarketingGrowth)^(C7-1) | D22: =FixedMarketingMonth*(1+FixedMarketingGrowth)^(D7-1) | E22: =FixedMarketingMonth*(1+FixedMarketingGrowth)^(E7-1) | F22: =FixedMarketingMonth*(1+FixedMarketingGrowth)^(F7-1) | G22: =FixedMarketingMonth*(1+FixedMarketingGrowth)^(G7-1) | H22: =FixedMarketingMonth*(1+FixedMarketingGrowth)^(H7-1) | I22: =FixedMarketingMonth*(1+FixedMarketingGrowth)^(I7-1) | J22: =FixedMarketingMonth*(1+FixedMarketingGrowth)^(J7-1) | ... AL22: =FixedMarketingMonth*(1+FixedMarketingGrowth)^(AL7-1) | AM22: =SUM(C22:N22) | AN22: =SUM(O22:Z22) | AO22: =SUM(AA22:AL22) | AP22: =SUM(AM22:AO22)
A23: Marketing variable | B23: € | C23: =INDEX(ScenarioMatrix,8,$B$3)*C15 | D23: =INDEX(ScenarioMatrix,8,$B$3)*D15 | E23: =INDEX(ScenarioMatrix,8,$B$3)*E15 | F23: =INDEX(ScenarioMatrix,8,$B$3)*F15 | G23: =INDEX(ScenarioMatrix,8,$B$3)*G15 | H23: =INDEX(ScenarioMatrix,8,$B$3)*H15 | I23: =INDEX(ScenarioMatrix,8,$B$3)*I15 | J23: =INDEX(ScenarioMatrix,8,$B$3)*J15 | ... AL23: =INDEX(ScenarioMatrix,8,$B$3)*AL15 | AM23: =SUM(C23:N23) | AN23: =SUM(O23:Z23) | AO23: =SUM(AA23:AL23) | AP23: =SUM(AM23:AO23)
A24: Otros gastos | B24: € | C24: =OtherOpexMonth*INDEX(ScenarioMatrix,9,$B$3)*(1+INDEX(ScenarioMatrix,10,$B$3))^(C7-1) | D24: =OtherOpexMonth*INDEX(ScenarioMatrix,9,$B$3)*(1+INDEX(ScenarioMatrix,10,$B$3))^(D7-1) | E24: =OtherOpexMonth*INDEX(ScenarioMatrix,9,$B$3)*(1+INDEX(ScenarioMatrix,10,$B$3))^(E7-1) | F24: =OtherOpexMonth*INDEX(ScenarioMatrix,9,$B$3)*(1+INDEX(ScenarioMatrix,10,$B$3))^(F7-1) | G24: =OtherOpexMonth*INDEX(ScenarioMatrix,9,$B$3)*(1+INDEX(ScenarioMatrix,10,$B$3))^(G7-1) | H24: =OtherOpexMonth*INDEX(ScenarioMatrix,9,$B$3)*(1+INDEX(ScenarioMatrix,10,$B$3))^(H7-1) | I24: =OtherOpexMonth*INDEX(ScenarioMatrix,9,$B$3)*(1+INDEX(ScenarioMatrix,10,$B$3))^(I7-1) | J24: =OtherOpexMonth*INDEX(ScenarioMatrix,9,$B$3)*(1+INDEX(ScenarioMatrix,10,$B$3))^(J7-1) | ... AL24: =OtherOpexMonth*INDEX(ScenarioMatrix,9,$B$3)*(1+INDEX(ScenarioMatrix,10,$B$3))^(AL7-1) | AM24: =SUM(C24:N24) | AN24: =SUM(O24:Z24) | AO24: =SUM(AA24:AL24) | AP24: =SUM(AM24:AO24)
A25: Total opex + personal | B25: € | C25: =SUM(C18:C24) | D25: =SUM(D18:D24) | E25: =SUM(E18:E24) | F25: =SUM(F18:F24) | G25: =SUM(G18:G24) | H25: =SUM(H18:H24) | I25: =SUM(I18:I24) | J25: =SUM(J18:J24) | ... AL25: =SUM(AL18:AL24) | AM25: =SUM(C25:N25) | AN25: =SUM(O25:Z25) | AO25: =SUM(AA25:AL25) | AP25: =SUM(AM25:AO25)
A26: EBITDA | B26: € | C26: =C17-C25 | D26: =D17-D25 | E26: =E17-E25 | F26: =F17-F25 | G26: =G17-G25 | H26: =H17-H25 | I26: =I17-I25 | J26: =J17-J25 | ... AL26: =AL17-AL25 | AM26: =SUM(C26:N26) | AN26: =SUM(O26:Z26) | AO26: =SUM(AA26:AL26) | AP26: =SUM(AM26:AO26)
A27: Amortización | B27: € | C27: =MonthlyDepreciation | D27: =MonthlyDepreciation | E27: =MonthlyDepreciation | F27: =MonthlyDepreciation | G27: =MonthlyDepreciation | H27: =MonthlyDepreciation | I27: =MonthlyDepreciation | J27: =MonthlyDepreciation | ... AL27: =MonthlyDepreciation | AM27: =SUM(C27:N27) | AN27: =SUM(O27:Z27) | AO27: =SUM(AA27:AL27) | AP27: =SUM(AM27:AO27)
A28: EBIT | B28: € | C28: =C26-C27 | D28: =D26-D27 | E28: =E26-E27 | F28: =F26-F27 | G28: =G26-G27 | H28: =H26-H27 | I28: =I26-I27 | J28: =J26-J27 | ... AL28: =AL26-AL27 | AM28: =SUM(C28:N28) | AN28: =SUM(O28:Z28) | AO28: =SUM(AA28:AL28) | AP28: =SUM(AM28:AO28)
A29: Intereses | B29: € | C29: =C53 | D29: =D53 | E29: =E53 | F29: =F53 | G29: =G53 | H29: =H53 | I29: =I53 | J29: =J53 | ... AL29: =AL53 | AM29: =SUM(C29:N29) | AN29: =SUM(O29:Z29) | AO29: =SUM(AA29:AL29) | AP29: =SUM(AM29:AO29)
A30: EBT | B30: € | C30: =C28-C29 | D30: =D28-D29 | E30: =E28-E29 | F30: =F28-F29 | G30: =G28-G29 | H30: =H28-H29 | I30: =I28-I29 | J30: =J28-J29 | ... AL30: =AL28-AL29 | AM30: =SUM(C30:N30) | AN30: =SUM(O30:Z30) | AO30: =SUM(AA30:AL30) | AP30: =SUM(AM30:AO30)
A31: Impuestos | B31: € | C31: =IF(C7=1,$B$63/12,IF(C7=2,$C$63/12,$D$63/12)) | D31: =IF(D7=1,$B$63/12,IF(D7=2,$C$63/12,$D$63/12)) | E31: =IF(E7=1,$B$63/12,IF(E7=2,$C$63/12,$D$63/12)) | F31: =IF(F7=1,$B$63/12,IF(F7=2,$C$63/12,$D$63/12)) | G31: =IF(G7=1,$B$63/12,IF(G7=2,$C$63/12,$D$63/12)) | H31: =IF(H7=1,$B$63/12,IF(H7=2,$C$63/12,$D$63/12)) | I31: =IF(I7=1,$B$63/12,IF(I7=2,$C$63/12,$D$63/12)) | J31: =IF(J7=1,$B$63/12,IF(J7=2,$C$63/12,$D$63/12)) | ... AL31: =IF(AL7=1,$B$63/12,IF(AL7=2,$C$63/12,$D$63/12)) | AM31: =SUM(C31:N31) | AN31: =SUM(O31:Z31) | AO31: =SUM(AA31:AL31) | AP31: =SUM(AM31:AO31)
A32: Beneficio neto | B32: € | C32: =C30-C31 | D32: =D30-D31 | E32: =E30-E31 | F32: =F30-F31 | G32: =G30-G31 | H32: =H30-H31 | I32: =I30-I31 | J32: =J30-J31 | ... AL32: =AL30-AL31 | AM32: =SUM(C32:N32) | AN32: =SUM(O32:Z32) | AO32: =SUM(AA32:AL32) | AP32: =SUM(AM32:AO32)
A33: Margen bruto % | B33: % | C33: =IFERROR(C17/C15,0) | D33: =IFERROR(D17/D15,0) | E33: =IFERROR(E17/E15,0) | F33: =IFERROR(F17/F15,0) | G33: =IFERROR(G17/G15,0) | H33: =IFERROR(H17/H15,0) | I33: =IFERROR(I17/I15,0) | J33: =IFERROR(J17/J15,0) | ... AP33: =IFERROR(AP17/AP15,0)
A34: Margen EBITDA % | B34: % | C34: =IFERROR(C26/C15,0) | D34: =IFERROR(D26/D15,0) | E34: =IFERROR(E26/E15,0) | F34: =IFERROR(F26/F15,0) | G34: =IFERROR(G26/G15,0) | H34: =IFERROR(H26/H15,0) | I34: =IFERROR(I26/I15,0) | J34: =IFERROR(J26/J15,0) | ... AP34: =IFERROR(AP26/AP15,0)
A35: Margen neto % | B35: % | C35: =IFERROR(C32/C15,0) | D35: =IFERROR(D32/D15,0) | E35: =IFERROR(E32/E15,0) | F35: =IFERROR(F32/F15,0) | G35: =IFERROR(G32/G15,0) | H35: =IFERROR(H32/H15,0) | I35: =IFERROR(I32/I15,0) | J35: =IFERROR(J32/J15,0) | ... AP35: =IFERROR(AP32/AP15,0)
A36: Check P&L (debe ser 0) | B36: € | C36: =C17-C25-C26 | D36: =D17-D25-D26 | E36: =E17-E25-E26 | F36: =F17-F25-F26 | G36: =G17-G25-G26 | H36: =H17-H25-H26 | I36: =I17-I25-I26 | J36: =J17-J25-J26 | ... AO36: =AO17-AO25-AO26 | AP36: =SUM(AM36:AO36)
A37: CAJA
A38: Caja inicial | B38: € | C38: =OpeningCash | D38: =C48 | E38: =D48 | F38: =E48 | G38: =F48 | H38: =G48 | I38: =H48 | J38: =I48 | K38: =J48 | ... AL38: =AK48 | AM38: =N38 | AN38: =Z38 | AO38: =AL38 | AP38: =AO38
A39: Capital circulante | B39: € | C39: =C16*(InventoryDays-PayableDays)/365 | D39: =D16*(InventoryDays-PayableDays)/365 | E39: =E16*(InventoryDays-PayableDays)/365 | F39: =F16*(InventoryDays-PayableDays)/365 | G39: =G16*(InventoryDays-PayableDays)/365 | H39: =H16*(InventoryDays-PayableDays)/365 | I39: =I16*(InventoryDays-PayableDays)/365 | J39: =J16*(InventoryDays-PayableDays)/365 | ... AL39: =AL16*(InventoryDays-PayableDays)/365 | AM39: =N39 | AN39: =Z39 | AO39: =AL39 | AP39: =AO39
A40: Δ capital circulante | B40: € | C40: =C39-WC0 | D40: =D39-C39 | E40: =E39-D39 | F40: =F39-E39 | G40: =G39-F39 | H40: =H39-G39 | I40: =I39-H39 | J40: =J39-I39 | K40: =K39-J39 | ... AL40: =AL39-AK39 | AM40: =SUM(C40:N40) | AN40: =SUM(O40:Z40) | AO40: =SUM(AA40:AL40) | AP40: =SUM(AM40:AO40)
A41: Capex de mantenimiento | B41: € | C41: =C15*MaintenanceCapexPct | D41: =D15*MaintenanceCapexPct | E41: =E15*MaintenanceCapexPct | F41: =F15*MaintenanceCapexPct | G41: =G15*MaintenanceCapexPct | H41: =H15*MaintenanceCapexPct | I41: =I15*MaintenanceCapexPct | J41: =J15*MaintenanceCapexPct | ... AL41: =AL15*MaintenanceCapexPct | AM41: =SUM(C41:N41) | AN41: =SUM(O41:Z41) | AO41: =SUM(AA41:AL41) | AP41: =SUM(AM41:AO41)
A42: Impuesto teórico sin deuda | B42: € | C42: =IF(C7=1,$B$68/12,IF(C7=2,$C$68/12,$D$68/12)) | D42: =IF(D7=1,$B$68/12,IF(D7=2,$C$68/12,$D$68/12)) | E42: =IF(E7=1,$B$68/12,IF(E7=2,$C$68/12,$D$68/12)) | F42: =IF(F7=1,$B$68/12,IF(F7=2,$C$68/12,$D$68/12)) | G42: =IF(G7=1,$B$68/12,IF(G7=2,$C$68/12,$D$68/12)) | H42: =IF(H7=1,$B$68/12,IF(H7=2,$C$68/12,$D$68/12)) | I42: =IF(I7=1,$B$68/12,IF(I7=2,$C$68/12,$D$68/12)) | J42: =IF(J7=1,$B$68/12,IF(J7=2,$C$68/12,$D$68/12)) | ... AL42: =IF(AL7=1,$B$68/12,IF(AL7=2,$C$68/12,$D$68/12)) | AM42: =SUM(C42:N42) | AN42: =SUM(O42:Z42) | AO42: =SUM(AA42:AL42) | AP42: =SUM(AM42:AO42)
A43: FCFF | B43: € | C43: =C26-C42-C41-C40 | D43: =D26-D42-D41-D40 | E43: =E26-E42-E41-E40 | F43: =F26-F42-F41-F40 | G43: =G26-G42-G41-G40 | H43: =H26-H42-H41-H40 | I43: =I26-I42-I41-I40 | J43: =J26-J42-J41-J40 | ... AL43: =AL26-AL42-AL41-AL40 | AM43: =SUM(C43:N43) | AN43: =SUM(O43:Z43) | AO43: =SUM(AA43:AL43) | AP43: =SUM(AM43:AO43)
A44: Intereses | B44: € | C44: =C53 | D44: =D53 | E44: =E53 | F44: =F53 | G44: =G53 | H44: =H53 | I44: =I53 | J44: =J53 | ... AL44: =AL53 | AM44: =SUM(C44:N44) | AN44: =SUM(O44:Z44) | AO44: =SUM(AA44:AL44) | AP44: =SUM(AM44:AO44)
A45: Escudo fiscal | B45: € | C45: =C42-C31 | D45: =D42-D31 | E45: =E42-E31 | F45: =F42-F31 | G45: =G42-G31 | H45: =H42-H31 | I45: =I42-I31 | J45: =J42-J31 | ... AL45: =AL42-AL31 | AM45: =SUM(C45:N45) | AN45: =SUM(O45:Z45) | AO45: =SUM(AA45:AL45) | AP45: =SUM(AM45:AO45)
A46: Principal | B46: € | C46: =C54 | D46: =D54 | E46: =E54 | F46: =F54 | G46: =G54 | H46: =H54 | I46: =I54 | J46: =J54 | ... AL46: =AL54 | AM46: =SUM(C46:N46) | AN46: =SUM(O46:Z46) | AO46: =SUM(AA46:AL46) | AP46: =SUM(AM46:AO46)
A47: FCFE | B47: € | C47: =C43-C44+C45-C46 | D47: =D43-D44+D45-D46 | E47: =E43-E44+E45-E46 | F47: =F43-F44+F45-F46 | G47: =G43-G44+G45-G46 | H47: =H43-H44+H45-H46 | I47: =I43-I44+I45-I46 | J47: =J43-J44+J45-J46 | ... AL47: =AL43-AL44+AL45-AL46 | AM47: =SUM(C47:N47) | AN47: =SUM(O47:Z47) | AO47: =SUM(AA47:AL47) | AP47: =SUM(AM47:AO47)
A48: Caja final | B48: € | C48: =C38+C47 | D48: =D38+D47 | E48: =E38+E47 | F48: =F38+F47 | G48: =G38+G47 | H48: =H38+H47 | I48: =I38+I47 | J48: =J38+J47 | ... AL48: =AL38+AL47 | AM48: =N48 | AN48: =Z48 | AO48: =AL48 | AP48: =AO48
A49: Check caja mínima | B49: texto | C49: =IF(C48<MinCash,"Alerta","OK") | D49: =IF(D48<MinCash,"Alerta","OK") | E49: =IF(E48<MinCash,"Alerta","OK") | F49: =IF(F48<MinCash,"Alerta","OK") | G49: =IF(G48<MinCash,"Alerta","OK") | H49: =IF(H48<MinCash,"Alerta","OK") | I49: =IF(I48<MinCash,"Alerta","OK") | J49: =IF(J48<MinCash,"Alerta","OK") | ... AL49: =IF(AL48<MinCash,"Alerta","OK")
A50: Check caja (debe ser 0) | B50: € | C50: =C38+C47-C48 | D50: =D38+D47-D48 | E50: =E38+E47-E48 | F50: =F38+F47-F48 | G50: =G38+G47-G48 | H50: =H38+H47-H48 | I50: =I38+I47-I48 | J50: =J38+J47-J48 | ... AL50: =AL38+AL47-AL48 | AM50: =SUM(C50:N50) | AN50: =SUM(O50:Z50) | AO50: =SUM(AA50:AL50) | AP50: =SUM(AM50:AO50)
A51: CALENDARIO DE DEUDA
A52: Deuda inicial | B52: € | C52: =LoanAmount | D52: =C55 | E52: =D55 | F52: =E55 | G52: =F55 | H52: =G55 | I52: =H55 | J52: =I55 | K52: =J55 | ... AL52: =AK55 | AM52: =N52 | AN52: =Z52 | AO52: =AL52 | AP52: =AO52
A53: Intereses | B53: € | C53: =C52*LoanRate/12 | D53: =D52*LoanRate/12 | E53: =E52*LoanRate/12 | F53: =F52*LoanRate/12 | G53: =G52*LoanRate/12 | H53: =H52*LoanRate/12 | I53: =I52*LoanRate/12 | J53: =J52*LoanRate/12 | ... AL53: =AL52*LoanRate/12 | AM53: =SUM(C53:N53) | AN53: =SUM(O53:Z53) | AO53: =SUM(AA53:AL53) | AP53: =SUM(AM53:AO53)
A54: Principal | B54: € | C54: =MIN(LoanPayment-C53,C52) | D54: =MIN(LoanPayment-D53,D52) | E54: =MIN(LoanPayment-E53,E52) | F54: =MIN(LoanPayment-F53,F52) | G54: =MIN(LoanPayment-G53,G52) | H54: =MIN(LoanPayment-H53,H52) | I54: =MIN(LoanPayment-I53,I52) | J54: =MIN(LoanPayment-J53,J52) | ... AL54: =MIN(LoanPayment-AL53,AL52) | AM54: =SUM(C54:N54) | AN54: =SUM(O54:Z54) | AO54: =SUM(AA54:AL54) | AP54: =SUM(AM54:AO54)
A55: Deuda final | B55: € | C55: =C52-C54 | D55: =D52-D54 | E55: =E52-E54 | F55: =F52-F54 | G55: =G52-G54 | H55: =H52-H54 | I55: =I52-I54 | J55: =J52-J54 | ... AL55: =AL52-AL54 | AM55: =N55 | AN55: =Z55 | AO55: =AL55 | AP55: =AO55
A56: Cuota | B56: € | C56: =LoanPayment | D56: =LoanPayment | E56: =LoanPayment | F56: =LoanPayment | G56: =LoanPayment | H56: =LoanPayment | I56: =LoanPayment | J56: =LoanPayment | ... AL56: =LoanPayment | AM56: =SUM(C56:N56) | AN56: =SUM(O56:Z56) | AO56: =SUM(AA56:AL56) | AP56: =SUM(AM56:AO56)
A57: DSCR | B57: × | C57: =IFERROR((C26-C31)/(C53+C54),0) | D57: =IFERROR((D26-D31)/(D53+D54),0) | E57: =IFERROR((E26-E31)/(E53+E54),0) | F57: =IFERROR((F26-F31)/(F53+F54),0) | G57: =IFERROR((G26-G31)/(G53+G54),0) | H57: =IFERROR((H26-H31)/(H53+H54),0) | I57: =IFERROR((I26-I31)/(I53+I54),0) | J57: =IFERROR((J26-J31)/(J53+J54),0) | ... AP57: =IFERROR((AP26-AP31)/(AP53+AP54),0)
A58: IMPUESTO ANUAL Y PÉRDIDAS COMPENSABLES
A59: Concepto | B59: 2026 | C59: 2027 | D59: 2028 | E59: La cuota mensual de la fila 31 es la cuota anual / 12.
A60: EBT anual | B60: =AM30 | C60: =AN30 | D60: =AO30
A61: Pérdidas inicio (con deuda) | B61: 0 | C61: =B64 | D61: =C64
A62: Base imponible | B62: =MAX(0,B60-B61) | C62: =MAX(0,C60-C61) | D62: =MAX(0,D60-D61)
A63: Cuota | B63: =B62*TaxRate | C63: =C62*TaxRate | D63: =D62*TaxRate
A64: Pérdidas fin | B64: =B61-MIN(B61,MAX(0,B60))+MAX(0,-B60) | C64: =C61-MIN(C61,MAX(0,C60))+MAX(0,-C60) | D64: =D61-MIN(D61,MAX(0,D60))+MAX(0,-D60)
A65: EBIT anual | B65: =AM28 | C65: =AN28 | D65: =AO28
A66: Pérdidas inicio (sin deuda) | B66: 0 | C66: =B69 | D66: =C69
A67: Base imponible sin deuda | B67: =MAX(0,B65-B66) | C67: =MAX(0,C65-C66) | D67: =MAX(0,D65-D66)
A68: Cuota sin deuda | B68: =B67*TaxRate | C68: =C67*TaxRate | D68: =D67*TaxRate
A69: Pérdidas fin (sin deuda) | B69: =B66-MIN(B66,MAX(0,B65))+MAX(0,-B65) | C69: =C66-MIN(C66,MAX(0,C65))+MAX(0,-C65) | D69: =D66-MIN(D66,MAX(0,D65))+MAX(0,-D65)
A70: Escudo fiscal | B70: =B68-B63 | C70: =C68-C63 | D70: =D68-D63
A74: RESUMEN ANUAL
A75: Métrica | B75: 2026 | C75: 2027 | D75: 2028 | E75: 3 años
A76: Ingresos netos | B76: =AM15 | C76: =AN15 | D76: =AO15 | E76: =SUM(B76:D76)
A77: COGS | B77: =AM16 | C77: =AN16 | D77: =AO16 | E77: =SUM(B77:D77)
A78: Margen bruto | B78: =AM17 | C78: =AN17 | D78: =AO17 | E78: =SUM(B78:D78)
A79: Personal | B79: =AM18 | C79: =AN18 | D79: =AO18 | E79: =SUM(B79:D79)
A80: Alquiler | B80: =AM19 | C80: =AN19 | D80: =AO19 | E80: =SUM(B80:D80)
A81: Suministros | B81: =AM20 | C81: =AN20 | D81: =AO20 | E81: =SUM(B81:D81)
A82: Servicios fijos | B82: =AM21 | C82: =AN21 | D82: =AO21 | E82: =SUM(B82:D82)
A83: Marketing fijo | B83: =AM22 | C83: =AN22 | D83: =AO22 | E83: =SUM(B83:D83)
A84: Marketing variable | B84: =AM23 | C84: =AN23 | D84: =AO23 | E84: =SUM(B84:D84)
A85: Otros gastos | B85: =AM24 | C85: =AN24 | D85: =AO24 | E85: =SUM(B85:D85)
A86: EBITDA | B86: =AM26 | C86: =AN26 | D86: =AO26 | E86: =SUM(B86:D86)
A87: Amortización | B87: =AM27 | C87: =AN27 | D87: =AO27 | E87: =SUM(B87:D87)
A88: EBIT | B88: =AM28 | C88: =AN28 | D88: =AO28 | E88: =SUM(B88:D88)
A89: Intereses | B89: =AM29 | C89: =AN29 | D89: =AO29 | E89: =SUM(B89:D89)
A90: EBT | B90: =AM30 | C90: =AN30 | D90: =AO30 | E90: =SUM(B90:D90)
A91: Impuestos | B91: =AM31 | C91: =AN31 | D91: =AO31 | E91: =SUM(B91:D91)
A92: Beneficio neto | B92: =AM32 | C92: =AN32 | D92: =AO32 | E92: =SUM(B92:D92)
A93: CFO | B93: =B92+B87-AM40 | C93: =C92+C87-AN40 | D93: =D92+D87-AO40 | E93: =SUM(B93:D93)
A94: Capex mantenimiento | B94: =AM41 | C94: =AN41 | D94: =AO41 | E94: =SUM(B94:D94)
A95: FCFF | B95: =AM43 | C95: =AN43 | D95: =AO43 | E95: =SUM(B95:D95)
A96: Principal | B96: =AM46 | C96: =AN46 | D96: =AO46 | E96: =SUM(B96:D96)
A97: FCFE | B97: =AM47 | C97: =AN47 | D97: =AO47 | E97: =SUM(B97:D97)
A98: Caja final | B98: =N48 | C98: =Z48 | D98: =AL48 | E98: =D98
A99: Tickets/día | B99: =AM13/AM9 | C99: =AN13/AN9 | D99: =AO13/AO9 | E99: =SUM(B99:D99)/3
A100: Ticket medio neto | B100: =B76/AM13 | C100: =C76/AN13 | D100: =D76/AO13 | E100: =E76/SUM(AM13:AO13)
A101: Ticket medio con IVA | B101: =B100*1.1 | C101: =C100*1.1 | D101: =D100*1.1 | E101: =E100*1.1
A102: Punto de equilibrio EBITDA | B102: =(B79+B80+B81+B82+B83+B85)/((B76-B77-B84)/AM13)/AM9 | C102: =(C79+C80+C81+C82+C83+C85)/((C76-C77-C84)/AN13)/AN9 | D102: =(D79+D80+D81+D82+D83+D85)/((D76-D77-D84)/AO13)/AO9
A103: Punto de equilibrio total | B103: =(B79+B80+B81+B82+B83+B85+B87+B89)/((B76-B77-B84)/AM13)/AM9 | C103: =(C79+C80+C81+C82+C83+C85+C87+C89)/((C76-C77-C84)/AN13)/AN9 | D103: =(D79+D80+D81+D82+D83+D85+D87+D89)/((D76-D77-D84)/AO13)/AO9
A104: Margen de seguridad | B104: =(B99-B103)/B99 | C104: =(C99-C103)/C99 | D104: =(D99-D103)/D99
...

Sheet Optimista
A1: Cafetería Aurora — Escenario Optimista
A2: EUR, sin IVA. Solo se editan las hojas de entrada.
A3: Selector (1/2/3): | B3: 3 | C3: 1 = Pesimista · 2 = Base · 3 = Optimista
A4: Escenario: | B4: =CHOOSE(B3,"Pesimista","Base","Optimista") | C4: Cambia el selector para ver el mismo modelo con los supuestos de otro escenario.
A5: Índice de mes | B5: mes | C5: 1 | D5: =C5+1 | E5: =D5+1 | F5: =E5+1 | G5: =F5+1 | H5: =G5+1 | I5: =H5+1 | J5: =I5+1 | K5: =J5+1 | ... AL5: =AK5+1
A6: Fecha | B6: fecha | C6: =DATE(2026,1,1) | D6: =EDATE(C6,1) | E6: =EDATE(D6,1) | F6: =EDATE(E6,1) | G6: =EDATE(F6,1) | H6: =EDATE(G6,1) | I6: =EDATE(H6,1) | J6: =EDATE(I6,1) | K6: =EDATE(J6,1) | ... AL6: =EDATE(AK6,1)
A7: Año | B7: 1–3 | C7: =ROUNDUP(C5/12,0) | D7: =ROUNDUP(D5/12,0) | E7: =ROUNDUP(E5/12,0) | F7: =ROUNDUP(F5/12,0) | G7: =ROUNDUP(G5/12,0) | H7: =ROUNDUP(H5/12,0) | I7: =ROUNDUP(I5/12,0) | J7: =ROUNDUP(J5/12,0) | ... AL7: =ROUNDUP(AL5/12,0)
A8: Mes | B8: 1–12 | C8: =MOD(C5-1,12)+1 | D8: =MOD(D5-1,12)+1 | E8: =MOD(E5-1,12)+1 | F8: =MOD(F5-1,12)+1 | G8: =MOD(G5-1,12)+1 | H8: =MOD(H5-1,12)+1 | I8: =MOD(I5-1,12)+1 | J8: =MOD(J5-1,12)+1 | ... AL8: =MOD(AL5-1,12)+1
A9: Días operativos | B9: días | C9: =INDEX(OpeningDays,1,C8) | D9: =INDEX(OpeningDays,1,D8) | E9: =INDEX(OpeningDays,1,E8) | F9: =INDEX(OpeningDays,1,F8) | G9: =INDEX(OpeningDays,1,G8) | H9: =INDEX(OpeningDays,1,H8) | I9: =INDEX(OpeningDays,1,I8) | J9: =INDEX(OpeningDays,1,J8) | ... AL9: =INDEX(OpeningDays,1,AL8) | AM9: =SUM(C9:N9) | AN9: =SUM(O9:Z9) | AO9: =SUM(AA9:AL9) | AP9: =SUM(AM9:AO9)
A11: CUENTA DE RESULTADOS
A12: Tickets/día | B12: tickets/día | C12: =BaseTicketsDay*INDEX(ScenarioMatrix,1,$B$3)*(1+INDEX(ScenarioMatrix,2,$B$3))^(1-1)*INDEX(Seasonality,1,C8)*IF(1=1,INDEX(Ramp,1,C8),1) | D12: =BaseTicketsDay*INDEX(ScenarioMatrix,1,$B$3)*(1+INDEX(ScenarioMatrix,2,$B$3))^(1-1)*INDEX(Seasonality,1,D8)*IF(1=1,INDEX(Ramp,1,D8),1) | E12: =BaseTicketsDay*INDEX(ScenarioMatrix,1,$B$3)*(1+INDEX(ScenarioMatrix,2,$B$3))^(1-1)*INDEX(Seasonality,1,E8)*IF(1=1,INDEX(Ramp,1,E8),1) | F12: =BaseTicketsDay*INDEX(ScenarioMatrix,1,$B$3)*(1+INDEX(ScenarioMatrix,2,$B$3))^(1-1)*INDEX(Seasonality,1,F8)*IF(1=1,INDEX(Ramp,1,F8),1) | G12: =BaseTicketsDay*INDEX(ScenarioMatrix,1,$B$3)*(1+INDEX(ScenarioMatrix,2,$B$3))^(1-1)*INDEX(Seasonality,1,G8)*IF(1=1,INDEX(Ramp,1,G8),1) | H12: =BaseTicketsDay*INDEX(ScenarioMatrix,1,$B$3)*(1+INDEX(ScenarioMatrix,2,$B$3))^(1-1)*INDEX(Seasonality,1,H8)*IF(1=1,INDEX(Ramp,1,H8),1) | I12: =BaseTicketsDay*INDEX(ScenarioMatrix,1,$B$3)*(1+INDEX(ScenarioMatrix,2,$B$3))^(1-1)*INDEX(Seasonality,1,I8)*IF(1=1,INDEX(Ramp,1,I8),1) | J12: =BaseTicketsDay*INDEX(ScenarioMatrix,1,$B$3)*(1+INDEX(ScenarioMatrix,2,$B$3))^(1-1)*INDEX(Seasonality,1,J8)*IF(1=1,INDEX(Ramp,1,J8),1) | ... N12: =BaseTicketsDay*INDEX(ScenarioMatrix,1,$B$3)*(1+INDEX(ScenarioMatrix,2,$B$3))^(1-1)*INDEX(Seasonality,1,N8)*IF(1=1,INDEX(Ramp,1,N8),1) | O12: =BaseTicketsDay*INDEX(ScenarioMatrix,1,$B$3)*(1+INDEX(ScenarioMatrix,2,$B$3))^(2-1)*INDEX(Seasonality,1,O8)*IF(2=1,INDEX(Ramp,1,O8),1) | P12: =BaseTicketsDay*INDEX(ScenarioMatrix,1,$B$3)*(1+INDEX(ScenarioMatrix,2,$B$3))^(2-1)*INDEX(Seasonality,1,P8)*IF(2=1,INDEX(Ramp,1,P8),1) | Q12: =BaseTicketsDay*INDEX(ScenarioMatrix,1,$B$3)*(1+INDEX(ScenarioMatrix,2,$B$3))^(2-1)*INDEX(Seasonality,1,Q8)*IF(2=1,INDEX(Ramp,1,Q8),1) | R12: =BaseTicketsDay*INDEX(ScenarioMatrix,1,$B$3)*(1+INDEX(ScenarioMatrix,2,$B$3))^(2-1)*INDEX(Seasonality,1,R8)*IF(2=1,INDEX(Ramp,1,R8),1) | S12: =BaseTicketsDay*INDEX(ScenarioMatrix,1,$B$3)*(1+INDEX(ScenarioMatrix,2,$B$3))^(2-1)*INDEX(Seasonality,1,S8)*IF(2=1,INDEX(Ramp,1,S8),1) | T12: =BaseTicketsDay*INDEX(ScenarioMatrix,1,$B$3)*(1+INDEX(ScenarioMatrix,2,$B$3))^(2-1)*INDEX(Seasonality,1,T8)*IF(2=1,INDEX(Ramp,1,T8),1) | U12: =BaseTicketsDay*INDEX(ScenarioMatrix,1,$B$3)*(1+INDEX(ScenarioMatrix,2,$B$3))^(2-1)*INDEX(Seasonality,1,U8)*IF(2=1,INDEX(Ramp,1,U8),1) | V12: =BaseTicketsDay*INDEX(ScenarioMatrix,1,$B$3)*(1+INDEX(ScenarioMatrix,2,$B$3))^(2-1)*INDEX(Seasonality,1,V8)*IF(2=1,INDEX(Ramp,1,V8),1) | ... Z12: =BaseTicketsDay*INDEX(ScenarioMatrix,1,$B$3)*(1+INDEX(ScenarioMatrix,2,$B$3))^(2-1)*INDEX(Seasonality,1,Z8)*IF(2=1,INDEX(Ramp,1,Z8),1) | AA12: =BaseTicketsDay*INDEX(ScenarioMatrix,1,$B$3)*(1+INDEX(ScenarioMatrix,2,$B$3))^(3-1)*INDEX(Seasonality,1,AA8)*IF(3=1,INDEX(Ramp,1,AA8),1) | AB12: =BaseTicketsDay*INDEX(ScenarioMatrix,1,$B$3)*(1+INDEX(ScenarioMatrix,2,$B$3))^(3-1)*INDEX(Seasonality,1,AB8)*IF(3=1,INDEX(Ramp,1,AB8),1) | AC12: =BaseTicketsDay*INDEX(ScenarioMatrix,1,$B$3)*(1+INDEX(ScenarioMatrix,2,$B$3))^(3-1)*INDEX(Seasonality,1,AC8)*IF(3=1,INDEX(Ramp,1,AC8),1) | AD12: =BaseTicketsDay*INDEX(ScenarioMatrix,1,$B$3)*(1+INDEX(ScenarioMatrix,2,$B$3))^(3-1)*INDEX(Seasonality,1,AD8)*IF(3=1,INDEX(Ramp,1,AD8),1) | AE12: =BaseTicketsDay*INDEX(ScenarioMatrix,1,$B$3)*(1+INDEX(ScenarioMatrix,2,$B$3))^(3-1)*INDEX(Seasonality,1,AE8)*IF(3=1,INDEX(Ramp,1,AE8),1) | AF12: =BaseTicketsDay*INDEX(ScenarioMatrix,1,$B$3)*(1+INDEX(ScenarioMatrix,2,$B$3))^(3-1)*INDEX(Seasonality,1,AF8)*IF(3=1,INDEX(Ramp,1,AF8),1) | AG12: =BaseTicketsDay*INDEX(ScenarioMatrix,1,$B$3)*(1+INDEX(ScenarioMatrix,2,$B$3))^(3-1)*INDEX(Seasonality,1,AG8)*IF(3=1,INDEX(Ramp,1,AG8),1) | AH12: =BaseTicketsDay*INDEX(ScenarioMatrix,1,$B$3)*(1+INDEX(ScenarioMatrix,2,$B$3))^(3-1)*INDEX(Seasonality,1,AH8)*IF(3=1,INDEX(Ramp,1,AH8),1) | ... AL12: =BaseTicketsDay*INDEX(ScenarioMatrix,1,$B$3)*(1+INDEX(ScenarioMatrix,2,$B$3))^(3-1)*INDEX(Seasonality,1,AL8)*IF(3=1,INDEX(Ramp,1,AL8),1) | AM12: =SUM(C12:N12) | AN12: =SUM(O12:Z12) | AO12: =SUM(AA12:AL12) | AP12: =SUM(AM12:AO12)
A13: Tickets | B13: tickets | C13: =C12*C9 | D13: =D12*D9 | E13: =E12*E9 | F13: =F12*F9 | G13: =G12*G9 | H13: =H12*H9 | I13: =I12*I9 | J13: =J12*J9 | ... AL13: =AL12*AL9 | AM13: =SUM(C13:N13) | AN13: =SUM(O13:Z13) | AO13: =SUM(AA13:AL13) | AP13: =SUM(AM13:AO13)
A14: Ítems vendidos | B14: ítems | C14: =C13*ItemsPerTicket | D14: =D13*ItemsPerTicket | E14: =E13*ItemsPerTicket | F14: =F13*ItemsPerTicket | G14: =G13*ItemsPerTicket | H14: =H13*ItemsPerTicket | I14: =I13*ItemsPerTicket | J14: =J13*ItemsPerTicket | ... AL14: =AL13*ItemsPerTicket | AM14: =SUM(C14:N14) | AN14: =SUM(O14:Z14) | AO14: =SUM(AA14:AL14) | AP14: =SUM(AM14:AO14)
A15: Ingresos netos | B15: € | C15: =C14*WeightedNetPrice*(1+INDEX(ScenarioMatrix,3,$B$3))^(1-1) | D15: =D14*WeightedNetPrice*(1+INDEX(ScenarioMatrix,3,$B$3))^(1-1) | E15: =E14*WeightedNetPrice*(1+INDEX(ScenarioMatrix,3,$B$3))^(1-1) | F15: =F14*WeightedNetPrice*(1+INDEX(ScenarioMatrix,3,$B$3))^(1-1) | G15: =G14*WeightedNetPrice*(1+INDEX(ScenarioMatrix,3,$B$3))^(1-1) | H15: =H14*WeightedNetPrice*(1+INDEX(ScenarioMatrix,3,$B$3))^(1-1) | I15: =I14*WeightedNetPrice*(1+INDEX(ScenarioMatrix,3,$B$3))^(1-1) | J15: =J14*WeightedNetPrice*(1+INDEX(ScenarioMatrix,3,$B$3))^(1-1) | ... N15: =N14*WeightedNetPrice*(1+INDEX(ScenarioMatrix,3,$B$3))^(1-1) | O15: =O14*WeightedNetPrice*(1+INDEX(ScenarioMatrix,3,$B$3))^(2-1) | P15: =P14*WeightedNetPrice*(1+INDEX(ScenarioMatrix,3,$B$3))^(2-1) | Q15: =Q14*WeightedNetPrice*(1+INDEX(ScenarioMatrix,3,$B$3))^(2-1) | R15: =R14*WeightedNetPrice*(1+INDEX(ScenarioMatrix,3,$B$3))^(2-1) | S15: =S14*WeightedNetPrice*(1+INDEX(ScenarioMatrix,3,$B$3))^(2-1) | T15: =T14*WeightedNetPrice*(1+INDEX(ScenarioMatrix,3,$B$3))^(2-1) | U15: =U14*WeightedNetPrice*(1+INDEX(ScenarioMatrix,3,$B$3))^(2-1) | V15: =V14*WeightedNetPrice*(1+INDEX(ScenarioMatrix,3,$B$3))^(2-1) | ... Z15: =Z14*WeightedNetPrice*(1+INDEX(ScenarioMatrix,3,$B$3))^(2-1) | AA15: =AA14*WeightedNetPrice*(1+INDEX(ScenarioMatrix,3,$B$3))^(3-1) | AB15: =AB14*WeightedNetPrice*(1+INDEX(ScenarioMatrix,3,$B$3))^(3-1) | AC15: =AC14*WeightedNetPrice*(1+INDEX(ScenarioMatrix,3,$B$3))^(3-1) | AD15: =AD14*WeightedNetPrice*(1+INDEX(ScenarioMatrix,3,$B$3))^(3-1) | AE15: =AE14*WeightedNetPrice*(1+INDEX(ScenarioMatrix,3,$B$3))^(3-1) | AF15: =AF14*WeightedNetPrice*(1+INDEX(ScenarioMatrix,3,$B$3))^(3-1) | AG15: =AG14*WeightedNetPrice*(1+INDEX(ScenarioMatrix,3,$B$3))^(3-1) | AH15: =AH14*WeightedNetPrice*(1+INDEX(ScenarioMatrix,3,$B$3))^(3-1) | ... AL15: =AL14*WeightedNetPrice*(1+INDEX(ScenarioMatrix,3,$B$3))^(3-1) | AM15: =SUM(C15:N15) | AN15: =SUM(O15:Z15) | AO15: =SUM(AA15:AL15) | AP15: =SUM(AM15:AO15)
A16: COGS | B16: € | C16: =C14*WeightedCostAdj*(1+INDEX(ScenarioMatrix,4,$B$3))^(1-1) | D16: =D14*WeightedCostAdj*(1+INDEX(ScenarioMatrix,4,$B$3))^(1-1) | E16: =E14*WeightedCostAdj*(1+INDEX(ScenarioMatrix,4,$B$3))^(1-1) | F16: =F14*WeightedCostAdj*(1+INDEX(ScenarioMatrix,4,$B$3))^(1-1) | G16: =G14*WeightedCostAdj*(1+INDEX(ScenarioMatrix,4,$B$3))^(1-1) | H16: =H14*WeightedCostAdj*(1+INDEX(ScenarioMatrix,4,$B$3))^(1-1) | I16: =I14*WeightedCostAdj*(1+INDEX(ScenarioMatrix,4,$B$3))^(1-1) | J16: =J14*WeightedCostAdj*(1+INDEX(ScenarioMatrix,4,$B$3))^(1-1) | ... N16: =N14*WeightedCostAdj*(1+INDEX(ScenarioMatrix,4,$B$3))^(1-1) | O16: =O14*WeightedCostAdj*(1+INDEX(ScenarioMatrix,4,$B$3))^(2-1) | P16: =P14*WeightedCostAdj*(1+INDEX(ScenarioMatrix,4,$B$3))^(2-1) | Q16: =Q14*WeightedCostAdj*(1+INDEX(ScenarioMatrix,4,$B$3))^(2-1) | R16: =R14*WeightedCostAdj*(1+INDEX(ScenarioMatrix,4,$B$3))^(2-1) | S16: =S14*WeightedCostAdj*(1+INDEX(ScenarioMatrix,4,$B$3))^(2-1) | T16: =T14*WeightedCostAdj*(1+INDEX(ScenarioMatrix,4,$B$3))^(2-1) | U16: =U14*WeightedCostAdj*(1+INDEX(ScenarioMatrix,4,$B$3))^(2-1) | V16: =V14*WeightedCostAdj*(1+INDEX(ScenarioMatrix,4,$B$3))^(2-1) | ... Z16: =Z14*WeightedCostAdj*(1+INDEX(ScenarioMatrix,4,$B$3))^(2-1) | AA16: =AA14*WeightedCostAdj*(1+INDEX(ScenarioMatrix,4,$B$3))^(3-1) | AB16: =AB14*WeightedCostAdj*(1+INDEX(ScenarioMatrix,4,$B$3))^(3-1) | AC16: =AC14*WeightedCostAdj*(1+INDEX(ScenarioMatrix,4,$B$3))^(3-1) | AD16: =AD14*WeightedCostAdj*(1+INDEX(ScenarioMatrix,4,$B$3))^(3-1) | AE16: =AE14*WeightedCostAdj*(1+INDEX(ScenarioMatrix,4,$B$3))^(3-1) | AF16: =AF14*WeightedCostAdj*(1+INDEX(ScenarioMatrix,4,$B$3))^(3-1) | AG16: =AG14*WeightedCostAdj*(1+INDEX(ScenarioMatrix,4,$B$3))^(3-1) | AH16: =AH14*WeightedCostAdj*(1+INDEX(ScenarioMatrix,4,$B$3))^(3-1) | ... AL16: =AL14*WeightedCostAdj*(1+INDEX(ScenarioMatrix,4,$B$3))^(3-1) | AM16: =SUM(C16:N16) | AN16: =SUM(O16:Z16) | AO16: =SUM(AA16:AL16) | AP16: =SUM(AM16:AO16)
A17: Margen bruto | B17: € | C17: =C15-C16 | D17: =D15-D16 | E17: =E15-E16 | F17: =F15-F16 | G17: =G15-G16 | H17: =H15-H16 | I17: =I15-I16 | J17: =J15-J16 | ... AL17: =AL15-AL16 | AM17: =SUM(C17:N17) | AN17: =SUM(O17:Z17) | AO17: =SUM(AA17:AL17) | AP17: =SUM(AM17:AO17)
A18: Personal | B18: € | C18: =INDEX(StaffCostByYear,1,C7)*INDEX(ScenarioMatrix,5,$B$3)/12 | D18: =INDEX(StaffCostByYear,1,D7)*INDEX(ScenarioMatrix,5,$B$3)/12 | E18: =INDEX(StaffCostByYear,1,E7)*INDEX(ScenarioMatrix,5,$B$3)/12 | F18: =INDEX(StaffCostByYear,1,F7)*INDEX(ScenarioMatrix,5,$B$3)/12 | G18: =INDEX(StaffCostByYear,1,G7)*INDEX(ScenarioMatrix,5,$B$3)/12 | H18: =INDEX(StaffCostByYear,1,H7)*INDEX(ScenarioMatrix,5,$B$3)/12 | I18: =INDEX(StaffCostByYear,1,I7)*INDEX(ScenarioMatrix,5,$B$3)/12 | J18: =INDEX(StaffCostByYear,1,J7)*INDEX(ScenarioMatrix,5,$B$3)/12 | ... AL18: =INDEX(StaffCostByYear,1,AL7)*INDEX(ScenarioMatrix,5,$B$3)/12 | AM18: =SUM(C18:N18) | AN18: =SUM(O18:Z18) | AO18: =SUM(AA18:AL18) | AP18: =SUM(AM18:AO18)
A19: Alquiler | B19: € | C19: =RentMonth*INDEX(ScenarioMatrix,6,$B$3)*(1+RentGrowth)^(C7-1) | D19: =RentMonth*INDEX(ScenarioMatrix,6,$B$3)*(1+RentGrowth)^(D7-1) | E19: =RentMonth*INDEX(ScenarioMatrix,6,$B$3)*(1+RentGrowth)^(E7-1) | F19: =RentMonth*INDEX(ScenarioMatrix,6,$B$3)*(1+RentGrowth)^(F7-1) | G19: =RentMonth*INDEX(ScenarioMatrix,6,$B$3)*(1+RentGrowth)^(G7-1) | H19: =RentMonth*INDEX(ScenarioMatrix,6,$B$3)*(1+RentGrowth)^(H7-1) | I19: =RentMonth*INDEX(ScenarioMatrix,6,$B$3)*(1+RentGrowth)^(I7-1) | J19: =RentMonth*INDEX(ScenarioMatrix,6,$B$3)*(1+RentGrowth)^(J7-1) | ... AL19: =RentMonth*INDEX(ScenarioMatrix,6,$B$3)*(1+RentGrowth)^(AL7-1) | AM19: =SUM(C19:N19) | AN19: =SUM(O19:Z19) | AO19: =SUM(AA19:AL19) | AP19: =SUM(AM19:AO19)
A20: Suministros | B20: € | C20: =UtilitiesMonth*(1+INDEX(ScenarioMatrix,7,$B$3))^(C7-1) | D20: =UtilitiesMonth*(1+INDEX(ScenarioMatrix,7,$B$3))^(D7-1) | E20: =UtilitiesMonth*(1+INDEX(ScenarioMatrix,7,$B$3))^(E7-1) | F20: =UtilitiesMonth*(1+INDEX(ScenarioMatrix,7,$B$3))^(F7-1) | G20: =UtilitiesMonth*(1+INDEX(ScenarioMatrix,7,$B$3))^(G7-1) | H20: =UtilitiesMonth*(1+INDEX(ScenarioMatrix,7,$B$3))^(H7-1) | I20: =UtilitiesMonth*(1+INDEX(ScenarioMatrix,7,$B$3))^(I7-1) | J20: =UtilitiesMonth*(1+INDEX(ScenarioMatrix,7,$B$3))^(J7-1) | ... AL20: =UtilitiesMonth*(1+INDEX(ScenarioMatrix,7,$B$3))^(AL7-1) | AM20: =SUM(C20:N20) | AN20: =SUM(O20:Z20) | AO20: =SUM(AA20:AL20) | AP20: =SUM(AM20:AO20)
A21: Servicios fijos | B21: € | C21: =FixedServicesMonth*(1+INDEX(ScenarioMatrix,7,$B$3))^(C7-1) | D21: =FixedServicesMonth*(1+INDEX(ScenarioMatrix,7,$B$3))^(D7-1) | E21: =FixedServicesMonth*(1+INDEX(ScenarioMatrix,7,$B$3))^(E7-1) | F21: =FixedServicesMonth*(1+INDEX(ScenarioMatrix,7,$B$3))^(F7-1) | G21: =FixedServicesMonth*(1+INDEX(ScenarioMatrix,7,$B$3))^(G7-1) | H21: =FixedServicesMonth*(1+INDEX(ScenarioMatrix,7,$B$3))^(H7-1) | I21: =FixedServicesMonth*(1+INDEX(ScenarioMatrix,7,$B$3))^(I7-1) | J21: =FixedServicesMonth*(1+INDEX(ScenarioMatrix,7,$B$3))^(J7-1) | ... AL21: =FixedServicesMonth*(1+INDEX(ScenarioMatrix,7,$B$3))^(AL7-1) | AM21: =SUM(C21:N21) | AN21: =SUM(O21:Z21) | AO21: =SUM(AA21:AL21) | AP21: =SUM(AM21:AO21)
A22: Marketing fijo | B22: € | C22: =FixedMarketingMonth*(1+FixedMarketingGrowth)^(C7-1) | D22: =FixedMarketingMonth*(1+FixedMarketingGrowth)^(D7-1) | E22: =FixedMarketingMonth*(1+FixedMarketingGrowth)^(E7-1) | F22: =FixedMarketingMonth*(1+FixedMarketingGrowth)^(F7-1) | G22: =FixedMarketingMonth*(1+FixedMarketingGrowth)^(G7-1) | H22: =FixedMarketingMonth*(1+FixedMarketingGrowth)^(H7-1) | I22: =FixedMarketingMonth*(1+FixedMarketingGrowth)^(I7-1) | J22: =FixedMarketingMonth*(1+FixedMarketingGrowth)^(J7-1) | ... AL22: =FixedMarketingMonth*(1+FixedMarketingGrowth)^(AL7-1) | AM22: =SUM(C22:N22) | AN22: =SUM(O22:Z22) | AO22: =SUM(AA22:AL22) | AP22: =SUM(AM22:AO22)
A23: Marketing variable | B23: € | C23: =INDEX(ScenarioMatrix,8,$B$3)*C15 | D23: =INDEX(ScenarioMatrix,8,$B$3)*D15 | E23: =INDEX(ScenarioMatrix,8,$B$3)*E15 | F23: =INDEX(ScenarioMatrix,8,$B$3)*F15 | G23: =INDEX(ScenarioMatrix,8,$B$3)*G15 | H23: =INDEX(ScenarioMatrix,8,$B$3)*H15 | I23: =INDEX(ScenarioMatrix,8,$B$3)*I15 | J23: =INDEX(ScenarioMatrix,8,$B$3)*J15 | ... AL23: =INDEX(ScenarioMatrix,8,$B$3)*AL15 | AM23: =SUM(C23:N23) | AN23: =SUM(O23:Z23) | AO23: =SUM(AA23:AL23) | AP23: =SUM(AM23:AO23)
A24: Otros gastos | B24: € | C24: =OtherOpexMonth*INDEX(ScenarioMatrix,9,$B$3)*(1+INDEX(ScenarioMatrix,10,$B$3))^(C7-1) | D24: =OtherOpexMonth*INDEX(ScenarioMatrix,9,$B$3)*(1+INDEX(ScenarioMatrix,10,$B$3))^(D7-1) | E24: =OtherOpexMonth*INDEX(ScenarioMatrix,9,$B$3)*(1+INDEX(ScenarioMatrix,10,$B$3))^(E7-1) | F24: =OtherOpexMonth*INDEX(ScenarioMatrix,9,$B$3)*(1+INDEX(ScenarioMatrix,10,$B$3))^(F7-1) | G24: =OtherOpexMonth*INDEX(ScenarioMatrix,9,$B$3)*(1+INDEX(ScenarioMatrix,10,$B$3))^(G7-1) | H24: =OtherOpexMonth*INDEX(ScenarioMatrix,9,$B$3)*(1+INDEX(ScenarioMatrix,10,$B$3))^(H7-1) | I24: =OtherOpexMonth*INDEX(ScenarioMatrix,9,$B$3)*(1+INDEX(ScenarioMatrix,10,$B$3))^(I7-1) | J24: =OtherOpexMonth*INDEX(ScenarioMatrix,9,$B$3)*(1+INDEX(ScenarioMatrix,10,$B$3))^(J7-1) | ... AL24: =OtherOpexMonth*INDEX(ScenarioMatrix,9,$B$3)*(1+INDEX(ScenarioMatrix,10,$B$3))^(AL7-1) | AM24: =SUM(C24:N24) | AN24: =SUM(O24:Z24) | AO24: =SUM(AA24:AL24) | AP24: =SUM(AM24:AO24)
A25: Total opex + personal | B25: € | C25: =SUM(C18:C24) | D25: =SUM(D18:D24) | E25: =SUM(E18:E24) | F25: =SUM(F18:F24) | G25: =SUM(G18:G24) | H25: =SUM(H18:H24) | I25: =SUM(I18:I24) | J25: =SUM(J18:J24) | ... AL25: =SUM(AL18:AL24) | AM25: =SUM(C25:N25) | AN25: =SUM(O25:Z25) | AO25: =SUM(AA25:AL25) | AP25: =SUM(AM25:AO25)
A26: EBITDA | B26: € | C26: =C17-C25 | D26: =D17-D25 | E26: =E17-E25 | F26: =F17-F25 | G26: =G17-G25 | H26: =H17-H25 | I26: =I17-I25 | J26: =J17-J25 | ... AL26: =AL17-AL25 | AM26: =SUM(C26:N26) | AN26: =SUM(O26:Z26) | AO26: =SUM(AA26:AL26) | AP26: =SUM(AM26:AO26)
A27: Amortización | B27: € | C27: =MonthlyDepreciation | D27: =MonthlyDepreciation | E27: =MonthlyDepreciation | F27: =MonthlyDepreciation | G27: =MonthlyDepreciation | H27: =MonthlyDepreciation | I27: =MonthlyDepreciation | J27: =MonthlyDepreciation | ... AL27: =MonthlyDepreciation | AM27: =SUM(C27:N27) | AN27: =SUM(O27:Z27) | AO27: =SUM(AA27:AL27) | AP27: =SUM(AM27:AO27)
A28: EBIT | B28: € | C28: =C26-C27 | D28: =D26-D27 | E28: =E26-E27 | F28: =F26-F27 | G28: =G26-G27 | H28: =H26-H27 | I28: =I26-I27 | J28: =J26-J27 | ... AL28: =AL26-AL27 | AM28: =SUM(C28:N28) | AN28: =SUM(O28:Z28) | AO28: =SUM(AA28:AL28) | AP28: =SUM(AM28:AO28)
A29: Intereses | B29: € | C29: =C53 | D29: =D53 | E29: =E53 | F29: =F53 | G29: =G53 | H29: =H53 | I29: =I53 | J29: =J53 | ... AL29: =AL53 | AM29: =SUM(C29:N29) | AN29: =SUM(O29:Z29) | AO29: =SUM(AA29:AL29) | AP29: =SUM(AM29:AO29)
A30: EBT | B30: € | C30: =C28-C29 | D30: =D28-D29 | E30: =E28-E29 | F30: =F28-F29 | G30: =G28-G29 | H30: =H28-H29 | I30: =I28-I29 | J30: =J28-J29 | ... AL30: =AL28-AL29 | AM30: =SUM(C30:N30) | AN30: =SUM(O30:Z30) | AO30: =SUM(AA30:AL30) | AP30: =SUM(AM30:AO30)
A31: Impuestos | B31: € | C31: =IF(C7=1,$B$63/12,IF(C7=2,$C$63/12,$D$63/12)) | D31: =IF(D7=1,$B$63/12,IF(D7=2,$C$63/12,$D$63/12)) | E31: =IF(E7=1,$B$63/12,IF(E7=2,$C$63/12,$D$63/12)) | F31: =IF(F7=1,$B$63/12,IF(F7=2,$C$63/12,$D$63/12)) | G31: =IF(G7=1,$B$63/12,IF(G7=2,$C$63/12,$D$63/12)) | H31: =IF(H7=1,$B$63/12,IF(H7=2,$C$63/12,$D$63/12)) | I31: =IF(I7=1,$B$63/12,IF(I7=2,$C$63/12,$D$63/12)) | J31: =IF(J7=1,$B$63/12,IF(J7=2,$C$63/12,$D$63/12)) | ... AL31: =IF(AL7=1,$B$63/12,IF(AL7=2,$C$63/12,$D$63/12)) | AM31: =SUM(C31:N31) | AN31: =SUM(O31:Z31) | AO31: =SUM(AA31:AL31) | AP31: =SUM(AM31:AO31)
A32: Beneficio neto | B32: € | C32: =C30-C31 | D32: =D30-D31 | E32: =E30-E31 | F32: =F30-F31 | G32: =G30-G31 | H32: =H30-H31 | I32: =I30-I31 | J32: =J30-J31 | ... AL32: =AL30-AL31 | AM32: =SUM(C32:N32) | AN32: =SUM(O32:Z32) | AO32: =SUM(AA32:AL32) | AP32: =SUM(AM32:AO32)
A33: Margen bruto % | B33: % | C33: =IFERROR(C17/C15,0) | D33: =IFERROR(D17/D15,0) | E33: =IFERROR(E17/E15,0) | F33: =IFERROR(F17/F15,0) | G33: =IFERROR(G17/G15,0) | H33: =IFERROR(H17/H15,0) | I33: =IFERROR(I17/I15,0) | J33: =IFERROR(J17/J15,0) | ... AP33: =IFERROR(AP17/AP15,0)
A34: Margen EBITDA % | B34: % | C34: =IFERROR(C26/C15,0) | D34: =IFERROR(D26/D15,0) | E34: =IFERROR(E26/E15,0) | F34: =IFERROR(F26/F15,0) | G34: =IFERROR(G26/G15,0) | H34: =IFERROR(H26/H15,0) | I34: =IFERROR(I26/I15,0) | J34: =IFERROR(J26/J15,0) | ... AP34: =IFERROR(AP26/AP15,0)
A35: Margen neto % | B35: % | C35: =IFERROR(C32/C15,0) | D35: =IFERROR(D32/D15,0) | E35: =IFERROR(E32/E15,0) | F35: =IFERROR(F32/F15,0) | G35: =IFERROR(G32/G15,0) | H35: =IFERROR(H32/H15,0) | I35: =IFERROR(I32/I15,0) | J35: =IFERROR(J32/J15,0) | ... AP35: =IFERROR(AP32/AP15,0)
A36: Check P&L (debe ser 0) | B36: € | C36: =C17-C25-C26 | D36: =D17-D25-D26 | E36: =E17-E25-E26 | F36: =F17-F25-F26 | G36: =G17-G25-G26 | H36: =H17-H25-H26 | I36: =I17-I25-I26 | J36: =J17-J25-J26 | ... AO36: =AO17-AO25-AO26 | AP36: =SUM(AM36:AO36)
A37: CAJA
A38: Caja inicial | B38: € | C38: =OpeningCash | D38: =C48 | E38: =D48 | F38: =E48 | G38: =F48 | H38: =G48 | I38: =H48 | J38: =I48 | K38: =J48 | ... AL38: =AK48 | AM38: =N38 | AN38: =Z38 | AO38: =AL38 | AP38: =AO38
A39: Capital circulante | B39: € | C39: =C16*(InventoryDays-PayableDays)/365 | D39: =D16*(InventoryDays-PayableDays)/365 | E39: =E16*(InventoryDays-PayableDays)/365 | F39: =F16*(InventoryDays-PayableDays)/365 | G39: =G16*(InventoryDays-PayableDays)/365 | H39: =H16*(InventoryDays-PayableDays)/365 | I39: =I16*(InventoryDays-PayableDays)/365 | J39: =J16*(InventoryDays-PayableDays)/365 | ... AL39: =AL16*(InventoryDays-PayableDays)/365 | AM39: =N39 | AN39: =Z39 | AO39: =AL39 | AP39: =AO39
A40: Δ capital circulante | B40: € | C40: =C39-WC0 | D40: =D39-C39 | E40: =E39-D39 | F40: =F39-E39 | G40: =G39-F39 | H40: =H39-G39 | I40: =I39-H39 | J40: =J39-I39 | K40: =K39-J39 | ... AL40: =AL39-AK39 | AM40: =SUM(C40:N40) | AN40: =SUM(O40:Z40) | AO40: =SUM(AA40:AL40) | AP40: =SUM(AM40:AO40)
A41: Capex de mantenimiento | B41: € | C41: =C15*MaintenanceCapexPct | D41: =D15*MaintenanceCapexPct | E41: =E15*MaintenanceCapexPct | F41: =F15*MaintenanceCapexPct | G41: =G15*MaintenanceCapexPct | H41: =H15*MaintenanceCapexPct | I41: =I15*MaintenanceCapexPct | J41: =J15*MaintenanceCapexPct | ... AL41: =AL15*MaintenanceCapexPct | AM41: =SUM(C41:N41) | AN41: =SUM(O41:Z41) | AO41: =SUM(AA41:AL41) | AP41: =SUM(AM41:AO41)
A42: Impuesto teórico sin deuda | B42: € | C42: =IF(C7=1,$B$68/12,IF(C7=2,$C$68/12,$D$68/12)) | D42: =IF(D7=1,$B$68/12,IF(D7=2,$C$68/12,$D$68/12)) | E42: =IF(E7=1,$B$68/12,IF(E7=2,$C$68/12,$D$68/12)) | F42: =IF(F7=1,$B$68/12,IF(F7=2,$C$68/12,$D$68/12)) | G42: =IF(G7=1,$B$68/12,IF(G7=2,$C$68/12,$D$68/12)) | H42: =IF(H7=1,$B$68/12,IF(H7=2,$C$68/12,$D$68/12)) | I42: =IF(I7=1,$B$68/12,IF(I7=2,$C$68/12,$D$68/12)) | J42: =IF(J7=1,$B$68/12,IF(J7=2,$C$68/12,$D$68/12)) | ... AL42: =IF(AL7=1,$B$68/12,IF(AL7=2,$C$68/12,$D$68/12)) | AM42: =SUM(C42:N42) | AN42: =SUM(O42:Z42) | AO42: =SUM(AA42:AL42) | AP42: =SUM(AM42:AO42)
A43: FCFF | B43: € | C43: =C26-C42-C41-C40 | D43: =D26-D42-D41-D40 | E43: =E26-E42-E41-E40 | F43: =F26-F42-F41-F40 | G43: =G26-G42-G41-G40 | H43: =H26-H42-H41-H40 | I43: =I26-I42-I41-I40 | J43: =J26-J42-J41-J40 | ... AL43: =AL26-AL42-AL41-AL40 | AM43: =SUM(C43:N43) | AN43: =SUM(O43:Z43) | AO43: =SUM(AA43:AL43) | AP43: =SUM(AM43:AO43)
A44: Intereses | B44: € | C44: =C53 | D44: =D53 | E44: =E53 | F44: =F53 | G44: =G53 | H44: =H53 | I44: =I53 | J44: =J53 | ... AL44: =AL53 | AM44: =SUM(C44:N44) | AN44: =SUM(O44:Z44) | AO44: =SUM(AA44:AL44) | AP44: =SUM(AM44:AO44)
A45: Escudo fiscal | B45: € | C45: =C42-C31 | D45: =D42-D31 | E45: =E42-E31 | F45: =F42-F31 | G45: =G42-G31 | H45: =H42-H31 | I45: =I42-I31 | J45: =J42-J31 | ... AL45: =AL42-AL31 | AM45: =SUM(C45:N45) | AN45: =SUM(O45:Z45) | AO45: =SUM(AA45:AL45) | AP45: =SUM(AM45:AO45)
A46: Principal | B46: € | C46: =C54 | D46: =D54 | E46: =E54 | F46: =F54 | G46: =G54 | H46: =H54 | I46: =I54 | J46: =J54 | ... AL46: =AL54 | AM46: =SUM(C46:N46) | AN46: =SUM(O46:Z46) | AO46: =SUM(AA46:AL46) | AP46: =SUM(AM46:AO46)
A47: FCFE | B47: € | C47: =C43-C44+C45-C46 | D47: =D43-D44+D45-D46 | E47: =E43-E44+E45-E46 | F47: =F43-F44+F45-F46 | G47: =G43-G44+G45-G46 | H47: =H43-H44+H45-H46 | I47: =I43-I44+I45-I46 | J47: =J43-J44+J45-J46 | ... AL47: =AL43-AL44+AL45-AL46 | AM47: =SUM(C47:N47) | AN47: =SUM(O47:Z47) | AO47: =SUM(AA47:AL47) | AP47: =SUM(AM47:AO47)
A48: Caja final | B48: € | C48: =C38+C47 | D48: =D38+D47 | E48: =E38+E47 | F48: =F38+F47 | G48: =G38+G47 | H48: =H38+H47 | I48: =I38+I47 | J48: =J38+J47 | ... AL48: =AL38+AL47 | AM48: =N48 | AN48: =Z48 | AO48: =AL48 | AP48: =AO48
A49: Check caja mínima | B49: texto | C49: =IF(C48<MinCash,"Alerta","OK") | D49: =IF(D48<MinCash,"Alerta","OK") | E49: =IF(E48<MinCash,"Alerta","OK") | F49: =IF(F48<MinCash,"Alerta","OK") | G49: =IF(G48<MinCash,"Alerta","OK") | H49: =IF(H48<MinCash,"Alerta","OK") | I49: =IF(I48<MinCash,"Alerta","OK") | J49: =IF(J48<MinCash,"Alerta","OK") | ... AL49: =IF(AL48<MinCash,"Alerta","OK")
A50: Check caja (debe ser 0) | B50: € | C50: =C38+C47-C48 | D50: =D38+D47-D48 | E50: =E38+E47-E48 | F50: =F38+F47-F48 | G50: =G38+G47-G48 | H50: =H38+H47-H48 | I50: =I38+I47-I48 | J50: =J38+J47-J48 | ... AL50: =AL38+AL47-AL48 | AM50: =SUM(C50:N50) | AN50: =SUM(O50:Z50) | AO50: =SUM(AA50:AL50) | AP50: =SUM(AM50:AO50)
A51: CALENDARIO DE DEUDA
A52: Deuda inicial | B52: € | C52: =LoanAmount | D52: =C55 | E52: =D55 | F52: =E55 | G52: =F55 | H52: =G55 | I52: =H55 | J52: =I55 | K52: =J55 | ... AL52: =AK55 | AM52: =N52 | AN52: =Z52 | AO52: =AL52 | AP52: =AO52
A53: Intereses | B53: € | C53: =C52*LoanRate/12 | D53: =D52*LoanRate/12 | E53: =E52*LoanRate/12 | F53: =F52*LoanRate/12 | G53: =G52*LoanRate/12 | H53: =H52*LoanRate/12 | I53: =I52*LoanRate/12 | J53: =J52*LoanRate/12 | ... AL53: =AL52*LoanRate/12 | AM53: =SUM(C53:N53) | AN53: =SUM(O53:Z53) | AO53: =SUM(AA53:AL53) | AP53: =SUM(AM53:AO53)
A54: Principal | B54: € | C54: =MIN(LoanPayment-C53,C52) | D54: =MIN(LoanPayment-D53,D52) | E54: =MIN(LoanPayment-E53,E52) | F54: =MIN(LoanPayment-F53,F52) | G54: =MIN(LoanPayment-G53,G52) | H54: =MIN(LoanPayment-H53,H52) | I54: =MIN(LoanPayment-I53,I52) | J54: =MIN(LoanPayment-J53,J52) | ... AL54: =MIN(LoanPayment-AL53,AL52) | AM54: =SUM(C54:N54) | AN54: =SUM(O54:Z54) | AO54: =SUM(AA54:AL54) | AP54: =SUM(AM54:AO54)
A55: Deuda final | B55: € | C55: =C52-C54 | D55: =D52-D54 | E55: =E52-E54 | F55: =F52-F54 | G55: =G52-G54 | H55: =H52-H54 | I55: =I52-I54 | J55: =J52-J54 | ... AL55: =AL52-AL54 | AM55: =N55 | AN55: =Z55 | AO55: =AL55 | AP55: =AO55
A56: Cuota | B56: € | C56: =LoanPayment | D56: =LoanPayment | E56: =LoanPayment | F56: =LoanPayment | G56: =LoanPayment | H56: =LoanPayment | I56: =LoanPayment | J56: =LoanPayment | ... AL56: =LoanPayment | AM56: =SUM(C56:N56) | AN56: =SUM(O56:Z56) | AO56: =SUM(AA56:AL56) | AP56: =SUM(AM56:AO56)
A57: DSCR | B57: × | C57: =IFERROR((C26-C31)/(C53+C54),0) | D57: =IFERROR((D26-D31)/(D53+D54),0) | E57: =IFERROR((E26-E31)/(E53+E54),0) | F57: =IFERROR((F26-F31)/(F53+F54),0) | G57: =IFERROR((G26-G31)/(G53+G54),0) | H57: =IFERROR((H26-H31)/(H53+H54),0) | I57: =IFERROR((I26-I31)/(I53+I54),0) | J57: =IFERROR((J26-J31)/(J53+J54),0) | ... AP57: =IFERROR((AP26-AP31)/(AP53+AP54),0)
A58: IMPUESTO ANUAL Y PÉRDIDAS COMPENSABLES
A59: Concepto | B59: 2026 | C59: 2027 | D59: 2028 | E59: La cuota mensual de la fila 31 es la cuota anual / 12.
A60: EBT anual | B60: =AM30 | C60: =AN30 | D60: =AO30
A61: Pérdidas inicio (con deuda) | B61: 0 | C61: =B64 | D61: =C64
A62: Base imponible | B62: =MAX(0,B60-B61) | C62: =MAX(0,C60-C61) | D62: =MAX(0,D60-D61)
A63: Cuota | B63: =B62*TaxRate | C63: =C62*TaxRate | D63: =D62*TaxRate
A64: Pérdidas fin | B64: =B61-MIN(B61,MAX(0,B60))+MAX(0,-B60) | C64: =C61-MIN(C61,MAX(0,C60))+MAX(0,-C60) | D64: =D61-MIN(D61,MAX(0,D60))+MAX(0,-D60)
A65: EBIT anual | B65: =AM28 | C65: =AN28 | D65: =AO28
A66: Pérdidas inicio (sin deuda) | B66: 0 | C66: =B69 | D66: =C69
A67: Base imponible sin deuda | B67: =MAX(0,B65-B66) | C67: =MAX(0,C65-C66) | D67: =MAX(0,D65-D66)
A68: Cuota sin deuda | B68: =B67*TaxRate | C68: =C67*TaxRate | D68: =D67*TaxRate
A69: Pérdidas fin (sin deuda) | B69: =B66-MIN(B66,MAX(0,B65))+MAX(0,-B65) | C69: =C66-MIN(C66,MAX(0,C65))+MAX(0,-C65) | D69: =D66-MIN(D66,MAX(0,D65))+MAX(0,-D65)
A70: Escudo fiscal | B70: =B68-B63 | C70: =C68-C63 | D70: =D68-D63
A74: RESUMEN ANUAL
A75: Métrica | B75: 2026 | C75: 2027 | D75: 2028 | E75: 3 años
A76: Ingresos netos | B76: =AM15 | C76: =AN15 | D76: =AO15 | E76: =SUM(B76:D76)
A77: COGS | B77: =AM16 | C77: =AN16 | D77: =AO16 | E77: =SUM(B77:D77)
A78: Margen bruto | B78: =AM17 | C78: =AN17 | D78: =AO17 | E78: =SUM(B78:D78)
A79: Personal | B79: =AM18 | C79: =AN18 | D79: =AO18 | E79: =SUM(B79:D79)
A80: Alquiler | B80: =AM19 | C80: =AN19 | D80: =AO19 | E80: =SUM(B80:D80)
A81: Suministros | B81: =AM20 | C81: =AN20 | D81: =AO20 | E81: =SUM(B81:D81)
A82: Servicios fijos | B82: =AM21 | C82: =AN21 | D82: =AO21 | E82: =SUM(B82:D82)
A83: Marketing fijo | B83: =AM22 | C83: =AN22 | D83: =AO22 | E83: =SUM(B83:D83)
A84: Marketing variable | B84: =AM23 | C84: =AN23 | D84: =AO23 | E84: =SUM(B84:D84)
A85: Otros gastos | B85: =AM24 | C85: =AN24 | D85: =AO24 | E85: =SUM(B85:D85)
A86: EBITDA | B86: =AM26 | C86: =AN26 | D86: =AO26 | E86: =SUM(B86:D86)
A87: Amortización | B87: =AM27 | C87: =AN27 | D87: =AO27 | E87: =SUM(B87:D87)
A88: EBIT | B88: =AM28 | C88: =AN28 | D88: =AO28 | E88: =SUM(B88:D88)
A89: Intereses | B89: =AM29 | C89: =AN29 | D89: =AO29 | E89: =SUM(B89:D89)
A90: EBT | B90: =AM30 | C90: =AN30 | D90: =AO30 | E90: =SUM(B90:D90)
A91: Impuestos | B91: =AM31 | C91: =AN31 | D91: =AO31 | E91: =SUM(B91:D91)
A92: Beneficio neto | B92: =AM32 | C92: =AN32 | D92: =AO32 | E92: =SUM(B92:D92)
A93: CFO | B93: =B92+B87-AM40 | C93: =C92+C87-AN40 | D93: =D92+D87-AO40 | E93: =SUM(B93:D93)
A94: Capex mantenimiento | B94: =AM41 | C94: =AN41 | D94: =AO41 | E94: =SUM(B94:D94)
A95: FCFF | B95: =AM43 | C95: =AN43 | D95: =AO43 | E95: =SUM(B95:D95)
A96: Principal | B96: =AM46 | C96: =AN46 | D96: =AO46 | E96: =SUM(B96:D96)
A97: FCFE | B97: =AM47 | C97: =AN47 | D97: =AO47 | E97: =SUM(B97:D97)
A98: Caja final | B98: =N48 | C98: =Z48 | D98: =AL48 | E98: =D98
A99: Tickets/día | B99: =AM13/AM9 | C99: =AN13/AN9 | D99: =AO13/AO9 | E99: =SUM(B99:D99)/3
A100: Ticket medio neto | B100: =B76/AM13 | C100: =C76/AN13 | D100: =D76/AO13 | E100: =E76/SUM(AM13:AO13)
A101: Ticket medio con IVA | B101: =B100*1.1 | C101: =C100*1.1 | D101: =D100*1.1 | E101: =E100*1.1
A102: Punto de equilibrio EBITDA | B102: =(B79+B80+B81+B82+B83+B85)/((B76-B77-B84)/AM13)/AM9 | C102: =(C79+C80+C81+C82+C83+C85)/((C76-C77-C84)/AN13)/AN9 | D102: =(D79+D80+D81+D82+D83+D85)/((D76-D77-D84)/AO13)/AO9
A103: Punto de equilibrio total | B103: =(B79+B80+B81+B82+B83+B85+B87+B89)/((B76-B77-B84)/AM13)/AM9 | C103: =(C79+C80+C81+C82+C83+C85+C87+C89)/((C76-C77-C84)/AN13)/AN9 | D103: =(D79+D80+D81+D82+D83+D85+D87+D89)/((D76-D77-D84)/AO13)/AO9
A104: Margen de seguridad | B104: =(B99-B103)/B99 | C104: =(C99-C103)/C99 | D104: =(D99-D103)/D99
...
